<?xml version="1.0" encoding="windows-1252" standalone="yes"?>
<!DOCTYPE document [
  <!ELEMENT document   (languageid,fields,page*)>
  <!ELEMENT languageid (#PCDATA)>
  <!ELEMENT fields     (Bron,Datum,Pagina)>
  <!ELEMENT Bron (#PCDATA)>
  <!ELEMENT Datum (#PCDATA)>
  <!ELEMENT Pagina (#PCDATA)>
  <!ELEMENT page       (pagenumber,text?,image?)>
  <!ELEMENT pagenumber (#PCDATA)>
  <!ELEMENT text       (#PCDATA)>
  <!ELEMENT image      (#PCDATA)>
  <!ATTLIST image      timestamp CDATA #REQUIRED
                       size      CDATA #REQUIRED>
]>
<document>
<languageid>21</languageid>
<fields>
<Bron>De Groene Amsterdammer</Bron>
<Datum>18780407</Datum>
<Pagina>2</Pagina>
</fields>
<page>
<pagenumber>1</pagenumber>
<text>
-il:
spo irwog ^\;v..ien - l.co;:.-, :tttl"i.. bet veis!.'. J MUI
de oom:.iis ie van i;ij.]U'iif.:rs over bot tontiacr n., t
de Huil. M.:eiou S, &gt;&gt;n.og Ma i'-eLap! ij ilui
/:-;;.ilam—Am-!erüain on l'ei.tiaal &gt;ta t.&gt;n.l. do ii:e:.ioi;e
van li&gt;'autWi&gt;.'Mii':g tot vvijxigii: : i'.tr v.ot t-ji l
lleogor on-lor1., ijs, t-» h.-" ra|ipo:'. uer ai'.l.-v'.ii f." n ov.-r
de oiiti-ijiPiiiiig-vn-t vi-or do s|-ovi\..-g A:ni.-i:
:'&gt;-n't-Nijmegen.

]!,! J/.i.v /r/s/-;'/!!/ K-V.IÜO tle/ovitv!-- ..Debor..ioivi„g
van tle l ola&gt;-tl.aro tiphreug-t tier .ïoboiiv.de
i-i^t-iidomiiio:;". _De nieuwe sta.iis-lceiiin.;", ,Ai.ix ei. de •
rijdende'artillerie". -Keu ht-it-i. k i';i..i.U-l"
(li\|'t'llu&gt;keul. .Aiustei-dum iu &gt;taat vau 1-elog". liiaaraaideid;:ig
van de bioohtire \au don lu-er tien Koer l'oortugna!l,
tieieohiolijko 9-tati.-iit.-k Min Nt-.loilaud tuer K-T(i'.
.liet woisoi.tweip betrtlVci.do don gt uoralon at ui",
Over L-uriitair.o".
DL' »V/Vi'(C' li- ,'t/•«''!•'i'ii:-i' had ;iiiiki!.-ii ovor Do
wet op 't nuiaiia.it", Do bola-iii'.g L.JI do siu\,-s.-ie
iu do rechte lijn", -Do vernieuwing dor hypothecaire

l!i-t Vnih'i-litiiil schreef o or \Voikeu
torveibetelilig dor bim.enlaiidsehc ieiivopvaait".
Jli. At'iiKi'ii'ir'l bevatte -T.'.k van publioko» itien-t:"

//f.' yi. iiii'? /'&lt;!,/ il, 11 l&gt;.i;i had: .Mi-handiliiig van
Jierou"'. Een bondgenoot iu den siryj vuur de vrij-1
vaart op 't NuouUcckaiaiai" l Mr. A. D. vau
-Ysstiidclt't de (.'oiiiugb iu r/r /.'".'/.D.W'.S.' van l April.
IL! l'tn'•/"•'.-'-In- J&gt;n;i!iliiil In-vatte: ,!lüf oi.twcrp
van wet op hot lager onderwijs" door den heer
1-aiucouihe SMUI.IITS
Iu Jii' Tftd k\v..'.ïi voor: ..Het gotlsdiciistoiuleiwijs
in het wetsontwerp Kapj-evue", ..Voorjaarsbuien on
Xajaarssiormeu", ,De im:a vnn don heer J. (:'. M.
vau Xisp n", _De minister van l!os=e over t
vvt-t.suutwcrp Kappuviie".
liï' AnJiiiii.-'li' (.'vini!.i'.l schroot'- rro.portioutv!o
vertegeuwoortligiiip', het ftel.-el -van Fiuiu", -Do
schoolwet en de liberale partij". _,-'.ui!;ainc".
Ulo. .-l'-.' a.lli;%.01tl'. lliOi. r._\ keil:.i:' g.-is.a.lkt. ell.'Oll
l', -ioti. :i.-eitt Ve;:-l.l;{ il:: l.-r t'i di l . .H.!: •.' ...u , .-l
lï.iu i ia s'aat ^l. Men. ei', ktfi.n • va» '......•:: o-.i.- i':-u
;L.V-; '.'.:•! It- i&gt;&lt;.';,Uvk!\ eji tlus aan Ie d:ii.Lr-lu te1 »i &gt;
Vlij'.i.^il .-Teil, We!''ü11.'tidig of UUiilg lll.joh ell liLjltvn
Io -ija. \Ve hopoti du dt'i- com-ui'.-ie !io'. i-;i::.i!»i:
\.t» zulk eou v.-i.-lag '..or.U- o. ge-lragou t-n /.ij ic-h
mot nauwgezetheid vau die /eicer HM ilgl. .
miuiihi.iig.-l lk!.u:.^'ij.&gt;e taak kitijteii i: il. 'i »mral ver

heugen w\j nu- 01. r de/.e piijing vau a 'r -uiiton,
ti.u.Lii /.ij tt-oiieii i:i !c i iel:, thit oeli l-i I.; •: mg, "O
uitiiiiiueiid ui- tk- boduolde, u.nii:eor zij biii.jit wordi
toeeepa.-t, /.t-or lich tl.-n wet-r/.in. uer bui gei j .-.uu
kunnen vv.kkoiï. indien «ij iu den !•&lt; .linie al te /.o.v
Itl h.'t k,»e-teieu vau ii'oiitin.itiu,- gi u-ven r.anLiditig
i, a l'. Niot /.oidou tia-h worden goode zakon \orworj en
of .voor iaugeii lijd o::iaoge'.i;'; g&gt;maakt, era,ia: .:ij
bij liaar oor.-io voiSvliijiaug do ..-el-u-ken haivr jen.;d
al to s.eik tioeii t'i.iioi'vindoii.
Do zaal van bot l'ronoot.-e'iap Na-au-a Ai'tis-
Ma«isirii. bekend uii.ï'er den naam v:-u tlo Koiiiiigr;:.!;-.!,
daar in-t lev.usgivot porti v-. \an '/.. M. aidaa;-
aaii\it-/ig i-,, \vortl na langen tijd op luiuaciitiici! go^tol.! te
ijii g.'«.vst. praohtiij geiostaiirooid. l'la!t':i.l o
wau.leii i'-.iju iu r.icin tiriekM-h.-.i &gt;tyl Ix.-ohild. rd
iUvr t'ii.'.ou ?t;u:gon&lt;»of, tien hoer F. l itu'ai!;. lu
het buitenland is tle.!e vvli/o van ' auii i'r.'d.-.i in;;
Vee.N laiig in /wang en voldoet ongouifon tk.or haii
sieiiykiioid ••» dii.irzaamheid. l'rui'. S.-hinki-l is de
uiuiiidi-r dezer methode, die alle vini_v!i ovtrlieit.
In het koninklijk slot te lieilyu il;n do nioes;e
zaleu op iUv.o w.j/.o \L-r-ierd.
Ivl'.^ST.
STADS/AKEX.
De Cte;nee!!;era:id' lieert in zijn zi'tiïig
van'de::tweek eindoüjk hot geluk gel...d h.-r ,.-ons to «ou-u.,
over tle geschikt lu-id van een ie: rein vuur Oen
groenten-, wiltl eu 'fruitmarkt. 1:11 de ;.'.aar-in.',' van
zulk oen -richtiiis: teg«-nuver hot in aa:.b..;,w /ijnde
rajkMiui.-eiim was ai'«ekor.id. Wol had lic:
l'r.uolyli-ch llesMtiir voorpesield do bloonien ook na .r
den ui'fn-inirel l-üdo l!.i.'iup&lt;&gt;-&gt;rt te vorbaiiiien.
maar tot onze blijd- 'u.ip hei-boii do Wt-;h...i-..l.-r
Tromp en ik- bo-.-r 5&gt;.!i;ni:z Je po.ti'-i'ho Iiii-.doroii
dei- natuur in bo.-oheini:i:u gtlwiiiou en lu-n boui-ed
voor een siuiu-liwniieli net de nuer pi'o;:a:?oiu'ii
iu zulk ec.li ver veiwi.lde.d om d. Ui.-^ eeliigo vraa,.
welke nog hc-aiitwoold rm-et wolden, is. «aar nu u.'
markt voor blosmon eeii p'.aa's z-1 eruino-u.' luoo
terreinen wt-.don ji.-r.oi-md. 'Het Ain,t,-iv.-ltl. wa.ir.'an
tie Wethouder van rubli-.-ke Wei ken. d. 'iuer Trou-.p.
en de heer (iu-n-hulk do voorkt-ur &gt;tiiL.nk&gt;.n. 011^ !ii-t.
pluntsuvu iiaa-t de liuliai.d-fin- (jWabriek. Mi--\!i;L-!i
wettn Iltni.-eniee.-ter vu We:'njudor- i-eu • ini_'
,u'e,K-hil:ter plaat- t,- vijlden. \v!j-iii?::o:i d.;: a; t,-. v.-aeh:eu.
/uólang wo die r.iet Vt-l-LuimMi, iaoar OLK o^~ het
Amst'olield hot mee ..t IL.O De jif-Ling linnen de
Etad. is voor c.on tu.irkt waar een zi-er'grout i..u;ia!
btirüóri belaiig in s.elkn. roéds op zi.^i i-:uli' ccn i;ro"-o
aiinbevtÜng. V-',..rdt Uc LCUUUW i-tU. ilat tb.' .-.'iiuoneu
hcibtlücn .zal., in h r.ur.'.i'X' IIK-'&gt; /iin bi'-ciiermiüg
ontvvc'i[jon on o; i:e:i'-iit, • t-;i w ij Jii'igeii ''.n
\-iwachten. i'.nn ::al dit iiïie.c- p'.t.u ii' U!--' v..,.:.:; l 'j
vviunoii. Ki.ii'k-n de l'..'eii.i-n. tiio u: •;. t!..ar w,-l. oijt
te- zien een l-'ir::aak i:ijia tl.it de -ai..;'':i'.eku- vtr hyiHeii
loods, bckeiitroni.hr deu-'!:.t 11; v.iri Am-.eÜivr:^ lu-l
..velu" 'ruimde, hoe tl.iiikb-irir /'--u iiu-ui-o
Aiu-leVdauimtv F!'-ra'/'^i..
Nott wOrJ i:i de/.c'.i'de u.-.-.l-.'.iiiir.i.u' &lt;-eU 'iie- ttr
sprake gi-brhcli-, d:(t. w-ólu.on weinig --oruehtmiihi:.'.)..
voor do br.i-gii'ö&lt; six.er 'st-d v.iti nk-t i;eii:i.yor
I.oteélifiiU is. ii,d;-ii li'-t -l.ji.lK-: '-"el l..-:d-. d::r 110
ii..lie«-aiiU'ii iliia'! iv.ce bi...'Ls:i. De li.-oien\V.
li,;i,Lkeu, I'ot, l!jij..'iolist&lt;.'in «n (jfo- challc \ei;z..ekei: n.n.!,...
lijk ilenKaaU een v.tl&gt;:el, in l.elii;iidflii,g te i:e..,! :i..
vo'c'etis 'hetwelk ilf- c. iiiini --io v;-.r &lt;ie. ryela'ue- iii
' zake de i.ia«:-eHj!;e diied.e ht.-U-.-tii),; iiuii'- het iiyü-men
•uiiweli'nodr.'d 'V-al w..uli-n &gt;f" b(.-r.ode:.t.t'rd,ver:-;:r; van
hare ondervinding ton opzi'ai'.'? er v.'üi'ki
van-gt;noeimlc .'hfl!as:iiig -vel' h.-t louja-i.de dioii.gaar uir
te b-oiiL'on. Men he-lo..t de.ie iui».-ivo U-r nadere
behand.iing ter vi-io te kgRi-n. liet'kaa niet audei.s
of aan geiioi'-:!'!L' c immi-.rie, dl'1 i.v'lui''.'lidc- het uoi'-.tc
jiiar -dat tl- uiiO'-TO b'-la"i;ig i.a.ir 'liet iukuii.i.-iU,
Voege;,a.-t.. intt e-jn 'liui'tl^'.-ivcon .uf &lt;i' aainal let-lai.
nicei'olithii he:-i';-lilooVcli .-preken. U ik- betrekkelijke
wnardo dol- bestaande .vei•yii'i'ni.iig J«iiluli)k geu-ii.di.-n.
Met de' luee-te gebreken, die . noudzakt-lylcerwiji tle
T o o S' i: K i..

IIi'liK-u we i-ot'il- vru^iiet- het in l'i-anlii'ijii vv-rl
i&gt;l&gt;.J:iii!; nuikC'iid (iruiuu ..KL-II lieriii'l'.t ('rocüs" Jfof de
tjoiii't.'lm.'/si'Ui-liiH'i'i'ii vun l»:-io-,-'oii.&lt; 1-11 .liuU'N A
J.KHHVn-.ci'-U-r. 'hier UT jtoik' ojyi.-Vi.C'1-il. l'i'-|ii-ukeii. ;\ir
!..u!;U-n tkui« s--U'..i'i.hviil i!-.'i/.i-i:He ?tnl\ oiv.iov \li'ii
tlti'l l'i'.-i-lr.i'niy ViTi'nnii.vlJ" in '.l'-u S;
ui--i.-lioii\vi't!i-;j .to ^:eii \v.'i'. .)&gt;M!I'-!. l't' 1',-it i i.iiii'.U^i.1
w.i.ii'd'.\au iit'-. i!r;i:ii:i i^ i\\\\ uuur i'ii^ l ''-vhu'UWil t'ii l.\ij'
!..'i&gt;:ik-n 011- tiiH iiüi.il in; i!t' ui.vu. :itii(.
Lic hoi-'tvhuM'^'.ou ,\-:iii Uci;;u:i.l \\vi.l 'i«.'i'! .'ii H t. r
v.-.ii (UL'U'ii Keer :!atiuii-lijk t'ii me', jjfvoi'l vuni-^o-i'i-Ul.
/.-•:.•''•!' uvcrJi'i.'.V'.-H L':-.l l:ij de :i;'.iujüi-ni:ii:ï'ii to ;'u-n
'.U- in.Mi invr.-Ti-ij.vVi lij di.- .'^-i-!ii:lu!.4iiii; tri'fli. h.-in
ii:^»-. i';U'lir. 'ij lu't ^\•L•l^•;•\ ii.'.L'.Mi \aït/.:ju uuli-j-d ktïnL
Mcvnr.'.w KiL-iii'1 «i-; ni uc l-'-rtf tul \an Mevr.
ii'Aiiiiii:li'-. di' daxvuii''.- V;ui li./L ,l'i.-ii^:oii.i: d'llvr.-c;
L-n \.ii'i'iil i» '« :iiii;iiui-!ioii!i.u' M-.-IH: livi JiUil-ik
te Uut'k'ii, dL'.ii' il'- \v:uuui-i .ai.L i ;i cio. k:':iL'lir \;in
II.ILII' -l'el, AU C".iii,ni;urau L-t-ii Alin'LH'iif uu,- hart
kivj'i vil *.i» fvu:[,a lus VI-KII ili-u InaXL-n guoilliai ti_'Lii
til i"t&gt; U uUvll ' v'i^l.l-' ', &gt;';J11 --ii -}'L'l V Cl UiCi:l.ïC U l i L'l L lol..
I;i 't i'.;/.i.u.'iL'!: aicni -^i'-J- F'jului.in to \VL»M!'_-JI
UTiiuM. N.ü! 4-11 w.ini' Ji'ar' zij c t r t iU' v n.' 'iij.it1
-Ailii'-uML-, ::r.i-r tij.- Uj lo.aio iltiL-lit'.1!" 'o 21011: vuuialhi
hoi lu'i'ki'iiitiiii:-it-oliLr' liiot lia:ir \\i'U::'\\a^ iiiirü1 ,-j".'i
a,'iii;i :.;[^:.u.' V»'t!;; ovii vci-cli:l iii-.-t. .'.i-.j. K. U.i.iii.
tt.o i'liJKi'iiar niet y[UtH.i--oii i-; IO^L-II tt-iii' rul aU
i-ik- vati 'TiiklitiU'-'. wo v. Liii'ti liu|'L'ii dal ::u laior in oi.-iiu
lilillltv.'1't." liLjoitilJÜt! t'll- IK tol' X'il Vul.k'i'H. 'Ximill?
\'. L' iia.tr Hl'. /.'.4OH. \\ cku-il l'.i.u- IIUUILI^L- li'j\:thi_;ij
l .'UL'..!',.!,'..-!! ii:i;.l :.,!- ill -U' '.•.! V,.'l : 'C V.'l -l i';' "'.il-L i 11 :| 1,1 •.'
11i.L-: ,'ji --- h-.t i' a:til :'.:L-&lt; u- /:,-ii. ..:: ,.j i;«t_( /.,•-:'.
voi'l s i'-a-o /."l iii.i'd:.;.' ii-....i-.üm.i LVÜ. i-t'-..-..-^-! !ii.,io
i.ia^i'-'i;.iv i'.-'.'ir 'o iii..K.;i. h:1 .'^ in u.iar ^'.-ii vio
;:;,n 10 - i;&lt;. j.-i.ijdf. &lt;- vvii' v';i l.:ij ;l..i.ii' M/^ r.\'! ..p'
i.c j.;. II-.L.I to iuii* oii X'i-jkt (tuL-• u\oi'.ii -M'ii iiiiiüii'i;
tn m i aivil .0 \..rr;^o.... 11 \.'at 't.-: \:-\i ',^i^:o uit-;,
.'il-.lniv.' \:in b'.uu'i.i "l- in- lu-i'.^'iii til uo ii'v!'
&gt;ii'..c-l' Ai- 111' li:.r.".-( il'Aii..t-it-i i'i- vi-rviiiik-n- iiiiniii.'
iL'i.»--.i /.'-oi- uo i. \\ rl \\ a • do IiL'i"n.f iiiL'.-r !Mji,|a'i*
liali v ..'llli.'tl. lna.Ll' 'i.i' ki'!l UI li''-1!' l"i ^;-rll k i\ ;üf;.l.
Al- t.'r i ;iL.u-rlijitL' hi i::doi;i':ii \.ui Aari'-iiti,.- vi.'!.a'i.-d
ik- lii.--.l' .i''' .i-.ll,-; 'i'&gt;Ji' '"-• ':l.i.H'..:i 1,1 1.1 t u m. vuui
ku'llji-li oll liO.'alvn.. " .
lic !-.i-'-|- \vU.iiiili -. i-it. "h,i" I.a/.'u-. iit- .-limüii;
li.L'Oi'ii :..i.'.!'. til'- la.L-r _ilo rul v.;-a i U'hiiall /.uo
,-_',".'i \V-ft U1 \l.'iVlli.Oli. V.0.'4'i lio'U' il.'il) Illvf ril'iaill
iu h:ij&gt;::iaai cuii a.ii'.n- \ nu. ^''--to.'i; it.ii .:.t';i.. 11 n
1'UIV'J \"jl' dtr j'jii3foj'i.ll'JU,V Sl yui', .illi: Ji l.u'
IX'i•li" iu l:oi'ga i.ai'iKiil.Ji; --| oi.-iii'-'.
Mi;t !.&lt;.&lt; l'ili.if* &lt;ii' ninni'li: v.111 Sir.ii,
-\'.';i'imj \vt";l; anïioüccojilon. ^;it' lift i'•
n.'h.:i;i-oh'Vr (lirixT'i-; .vun 'K-u li-.'f.ï1 I.-.-'
a\'Uinl ' ,&lt;le' l.".-li'i:it-c-voi'rlsti.'ll:iiy vau N
Vuitci'.il, 011 Xaioidag do ai-o!i. iii-ivuoi
.Vwteuil had ^'litil haar lioia-ac.!';«';
inissvïiien wi1-* 'f, ii:tf coii' •:—n 'k:ij!i!?--pn" 'a.Tu.-r. ci&gt; '
voor cnn van 't it!i"-r!ii'!(i''-'1« '&gt;H '''- IM] i'i-iu -n-h
vaivrlijk liiu' xij»'liont i.mtolo'.'.s vcriin:::dc'ii on xijn
luiin.-t-hnp lii;tii! 'ii. . ' ' ' '.
^\V:iiir!cIiijnlijlc .peil' ['n-'-iii.'it-r n::ii lanil
ai-'il'-riiPbleven, k!'.i&gt;ifem". Kti'lc «'t1 .f-tuui-iiiiin. hom ii:id&lt;'ifiiile:
nZC ninken tct'keiis a:in huid". • .
, ..Waals.hijuHjk, m:-iw lloot^". iiiitwriurililr • at.'
kapitein il'jodbo'lar.nl. •
»\Ve 'zulicn .turli niet onikee-ruii 't"
j^Occn gi'ciiif'.i'c! .10 hettt l«''!i pji'j'ï*i.i'' c.'1'in'.'K'"
r\ Sjirc'.-kt van »•:/. .. . A\\c.~. in unlo.'"
' . tfcji:., (10 dhr.,:;!.1'* '. • • ..
Verder1. Nvcrd cv uiof vor • jfo.o-.rokfn, n ct'njjfe
minuten hitcr .ym-r' ilo 1,-oot ook ret'il.s liijnr» &lt;hy,ir*
óver den 3Ii'---i "ifiiii. om ron venlorop
;{&lt;»!&lt;:^(;ii.zaiiilbank to ontwijken. I-'.r Iic-tohil ^cj-n inoi'olijkhoid
meer, dat iemand van den wal liuar kun vuluon.
' ' ' ' '' IV.'. ' ;'

1)1'. OM:I;V.U*IT I-EI: fTn-ijitnuf.

Nu e«rst', in liet vuile jrevofi «Ier vi-iliu!i':id, kon
llalfsou, die wfluilij': /elf &gt;i».a nirt V-óns ri-..-!i' oji xyii
' verlmnl wan K^konifiii. .n;iti xijn ^cli&lt;:!'il&lt;).(!(Mi'-&lt;vii.-c!i
libe by liunr IJJIT. &lt;nn hoord /.on hci'b.'i-^i'ii. 't. \\"as
nlle» zoo l&gt;nitcnj{ewonii ^|iw.!i^ y^.ini!, nuo i-cnalilaps
on'onvc'rwnchls Iji'gonnun, tii'^oviipid r-tt jLjo'iikt, dat ;
lig volstrekt Jiii;t ili fitaat Was pi-wve:&lt;t,.»|) do
liijzonderiiRden te lo'leii. :I)»nrl'ij hud hij no^'niêt. c.eii.s
recht govvcten, of zg xii-h weik'elijic'.vi-iiijj mochfi n
achten, of Stijtr pv\\efi'.c iiict wvr, nu hij haar ilanr
pas aan xijn zijde had, h'.-iii floor ton ttji-val ktin ont

rukt wordi;ii.
. Thftn» echter Instond i'.iiarvQDr &gt;ri«c.-)] \rect met-r.
D1 b &gt;ot fjli-ed in'iU-n duisteren. nnulit voort, Ui de
brnndendt1 luiiitM.-ipol:». die IMJ.' y.wi korl gi-lodi-n liimr
ui-\"»-Vi;&gt;- b:j:'li.'ii nvbi'M'lia 1de:i v :••; -•; ;''••!::, =••'
enic-r'loll l.ri hrtg Ml.inr iinl- véi-i-! i.s " -;i ' -i 'i- w /
j;sf*;r1V.I1. en viM''ltt'tM"li C!'i h-l-jk. -i; i\- ;-o ;t v; ei- 'i-f-ir
bocht, van den •&gt;'.&lt;•"» n v,'is o.n /-v r.- -.t. L,',-!»- i uii li"t

Maiir de. t',ic:!-j'iiig'-iJ'-'li:'n .••ti&gt;:i,!&gt;-:i i.n;r n) i,.... l
cuetleil, op h;;t.. lü'ichenil'-'c. d'j'i'r een !io-i;: ruv.- vin

ker.... en 't /«.ü-'.-fbi;» wa-i er Kuii'-rjiiïir-ngi'ijari'ii,
lat. l';ili"-im hoe e"r hoe beft-r daar^and,ian v;o:i.
Htioli Zoj	in m:n!-klo"reu, r-u dun t'ntg wel iu ecu
i' klel-'.lij'. d!" li.tiir'hi 'i gein-el niit pa ".&lt;j. iiraati. lian.r,
als aan d n kiiMitok, .IIMII d1?'M-liuii.!•':•&lt; hing: neei',
! dat' giliK H'i-'t.-cn !i:j 'wi-t n'è' hoe iiij i.ii-i'O'-n
jile'-j.-kon viinl-.'rt, waar-zy. zich g^vueglyk' zult kunnen

.Vi'ii'ii- iic.-U.ft'' «w goed/i", JeJin.vï" vrqt-ff hijktnr

Welke'kleuren'?" vroeg Jenny, liem verbn.iscl
aanzien'lc. '.'.
\Vel uit' kiecren, mij/i hlrt.... uw ei^eu klooi-eu:
want zóó "kunt j.'i: -tueh wa irlijl&gt; l.iitt in di: kajuit;
komc'li''. ' .
j ,.la ik liü'i. niets kiinren mccucMicn'', autwoorilde
l het mei je lneli' u&lt;l; _a!les'^'i:!g z.io gauw in iju werk,
j Dn mljii zii-jos^ hai'deii.iiuiiicr-s ti-rsiond alarm
gosla1 gen, nis ze ieni nid met ecu bundel onder den arm
j .uit ons huis hadden zien kinnen''. . . .
Óii;&lt; hebt ge ii:i:'s h'iegciu.-imd liiepgelioüienV'
| Niets 'lioé.'jeuïiftni'r', .au.woordd'; zij, hot, hoofd
' schxithlcnde, ,niets ter-«ereli!.....: dan uljeen
muilj liel'de voor .u", voi.-.'dn zij er lie:iijk bij.
i .Mijl lieve, zoete Jenny l o hoi: dank ik je
danrvnorl..1.. maar", vervolgde hij, tuuh wat vtrle^cn,
als ik IDI maar wi t. waar ik ge-cliikli! kleeicn vo. r
i j« l:uiv 1(1 ijgi-n.,.. VMitlt ik- u:»'.&lt;Mt lejfg.-u overal
| maar heel kort. aan", •
•' -Maar wat komf er da! op nati. r.ire.)n.i:i !...
kanik tlali niet zoo blijven, ars ik nu beu?''
Hui.... ja', mompelde Kalf-oii, je zint er zuo
i:raii'le :u:|Uc:;o i er .'!!;•: in. Van h.'t hegiit tot hot
i.:i.!e i&lt; ;-.ij d,&gt; h «' ij'.|-:u,.n, dit- die kuusi.'.ia vnn
v..'UVii.'!:j!;e «.-u -r;•/.•' .-;!.-li,-i.l 011 &gt;o!ia!k.,-hheid in 't
v.eik stel . t.".u vi-'ii hire vre...l:.i h, t geva irlijko
l ri, tje. 'io li.iiii':; • .;•"! ipilta- tle u.mie'.i •) te
voiovilen. 7.-J ktijiit. /.'H&gt;;'!s vau zelf s]'rc-.'kt, op 't hmt;4
h.iai- zin. C'j t|;ie foiume ve'.i', lüeu Ie Vf.it, on een
man op tioa Koop toe. Put uum'uver 't algemeen
haar gi.uo.'::eii \.il doen, lewiv.cn de stampvolle zaal
c.-i do ln'jt i'i'kruiis iiK't linden", die haar te;i deel vio!.
DJ tu-ei-li;e ixdieii waren i-ou weinig opgeofferd aan
re htuii'di c:- otin. Do leven lijfe Koiuóal als de
gedup t-rtV VHU llove. Mllo .Viniaii't Duvorgo ,«n zoo
vvo'iiii.' '.fioolu'iiisMiuo Mon.k-let zoo soiiindair, dit
nllf* i- togen do gottv.iiitc. De hoer Aub.-rt had de
perdaiitnil vau do ct.Mjilu.te Su.:annoj uaur ons idêi}
luid hij in dit -tuk, waar hoc /.oozoer op do
t-xplieatvs aankomt, e.wt-l wat iluidi-üjkur mogen geven;
in de eer-te ao e was h j tlikrt-yls moeilijk verstaan

baar. Mijschicu zijn diie acteu ook wel wat weinig
voor e.'n usoiid; men heeft gemeend het goud to
inako:) tloor laii^e pau/.ou en deze- te cNcuscüveu
door 00:10 ge;oi;;neeide nii-v-en so.'-ne.
Pebri.--a-bra"eol't-ctie in d.- tivoeji.- aeto hal echto;-, naar oliitk akt,
mot wat gooden w U wol iu l.'i minnten klaar ge^et
en iu ."i minuten weggeruimd kunne» zijn. Kniin, laat
.011$ nu, zeou-.'l genui volle avon Ion niet chieaneeren '
op vi;f minuten, i'e win:ii:i--.-;im;¥agno v:ui den heer !
i.oor it-, niet niet do» x'erdioudeu toeloop be^onnoii, !
hot i't zich steeil. iu mccv bijx'al iiio^ou vorheii^en, e»
wij sproken tien wonsc'.i van velen uit, wanneer w\j
bom ca zijn go/.e'.-chap loeroejien: Tot wedvrzicmt! l

In do Sahüi dos Vari'tés -- van de heoren .ludols en
l»,)itvi-nii-os!ei' werd in tien loop Uczcr week O; ge- i
voorii, «De ln.-'cetlrïin^", beroou-ul tlrama in ft
bedryveu tloor J. J. Soluiri'.r.um ••- schrij'.ei- van (iabrielle.
lioo t:t' tiat drauia beroemd is geworden verklaren
wij niet to weten, omdat o. i. tle beroemdheid eerst
i::i do o;..oeiiu-4' kan koiaon. Dit drama was hot
ivliu'r h!ijk,,'u.s tlo aauplakl'iiletteu reeds, vóór het aan
't publiek werd veito, ntl. Don titel ,de beleeuiging''
v ii.don wij goed gekezO.'. uuidiit. het tooiit-olprotlukt
van doZL'ii airour iu waarheid eeue lie'.eedigiiig is,
goeden smaak on gevoel aangedaan. Hot is niet ;
inog! bjjk don hihr.ud op to geven, xelfs niet dk.iaau
to diiitleii, daar we geen wio.ldeil kunnen vinden om i
het lioofilmotief van dit stuk. ,öp zulk eone wij/.e ;
inetk-titioolon dat gokui-olito doren niet er tloor
gei;v.e.-t woru,oii. Do /aak. di.' in du beleedigin:," wordt,
l'elMii.U'iil. ka:i iu eou iat--'..t-!iiijk ^e.-:el-cliap niet
\vor
i'o l-'ran .'lio nain..'ii dei' per-LHieu, tle g&gt; heel,o- he

li:: inleling vin ht-t tlr.il ia. tloen ons hopen dat -het.
geen ci.,oa v-.-rk, maar oone vertaling is vau een
fran-c!i ?::ik vau gering allooi; we hopen het voor
tien hoer Scu'irmann, omdat we bijii:i uier kuiiucn
goluoM-n, d.it ooii Ne..l..-1-lan lor nou weinig gejachte-van
den Hoeden Miiaak zijii'-r laiiiL;ent&gt;oteii, zoo weinig
oei bii tl vu.j r góedi1 zeden eu far-^oeil bezit. Kou di-.
£c'..ik ] ro:lukt to Icveixn ^t.^at gelijk !»•. t zich zelvon
voor altij.l het recht te ontnomen, voor liet tooueol
te arbeiden.
De uitvoering was zeer verdienstelijk : ecu beter
s'uk waardig.

I-V Knge'iïch:- [vri is hot niet eens over Morilz
Xeville: terwijl roniiiiigu blatieii redelijk met hom
ingi'iiüiiu.-n waron, selirijtt eeti criucus: ^De/e
kuiistenaar. die o:,, hot v. steland grooio triumt'en schijnt
gevierd te hei l en i- ons Z.V. tegengevallen, dat wij
rer.:i aau o.'iie niy-tiiieal ie gelooiden. Van al de
g'.ieiie c&gt;g'1ü-''h!-i';;'-ii &gt;!ie o-.i-: wai-en iitingek»n&lt;lii;d, i
lii'!.'--ii w.,i. tri" '.''een ou!v'l-.- -.vvuii ieii: lvrw:jl' mis
hfte'
-l
i-i-: ma-ir :ils
zó'i in il- l;jj'iït bi-eü.a...'. i!,i)i,...i-t ik wt
l-cnllt Wal de.il-.'i--'i er d;"l .vnn z'lUe'i
ku ii.--n.ziv t'ieh k".,i'rf|k-v"i:t('ll"ii, dat
uit.:" o.cdcr.i .hiM'fiovl'n.-ht zijt". .
IKn. w.iai'im'iiit-tL'.Sir'v . , • .
/./',/// cu Srfutitiiu; door .lo-e^hino (.üose, i&lt; als
n'. 114 ondoi' do wurkt-n opguno aen vau do
Hulden»eil.ilie. Als allo rumniis die een gulden waard ::yn,
daarin een plauU vurdionen, dun heli ik er uietatogeii
dat aan' l.i&lt;-M KU Sfluiilaic zulk een plaats verleend
is. Kon hitisvnder, die het mui xiju tloohters j^eeft,
versoh.ifi haar eenige aaiigeiiame oogeiil,likken; eu
het is kennelijk hot dool der sehrijfstur geweest de
lezeressen i'iut iilleen nangenaani, maar ook nuttig
bo/ig te houden. Kn ik, die geen luxere*, maar een
kver beu, hoh wel een en ander in,het boek gevon

den, dut door ons leden van hot niet-M-hoone go.-daeht
miijj ter hurte genomen worden. Is hot evenwel hot
doel des uitgevers iu de G'ildens-ediÜL' een serie van
uiisMxtitlr ron-uns Ie leveren, &lt;lie een bepaalde aan

winst ija voor onzt.- letterkunde, dau beu ik er niet
zeker vnu dut hy l.ir/it en S&lt;'h'.t,li«t" lüul pioeteu
opnemen,
\N iu ttc hooitlpei-j-oon is, zou ik niet kunnen zeg

gen. De huuidgeduehte zal zijn, dat een vrouw niet
gelukkig wordt dan door liefde en huiselijkheid. Om
dio gedaehte iu het lioht ie sU-llou, worde-i eeuigo
uiei-jos ten touneelo gevoertl, vun wie men reeds
tvi'Muud ziet, welke type zij moeien vertegenwoordi

gen. Hijna nl de personen hehlieii iets conveutiouool-i.
.leaiine (.'linton is de solioone taleiitvollp, maar
oouiijsziiis ovel&gt;p!inuon vrouw, die voor de kunst leeft
en voor den roem. Vau die.twee verwacht z(j al
haar geluk, liet is te voorzien, dut zij harten breken
on ongelukkig worden znl. Welnu, zij breekt drie
harten en haar eigen hart driemaal, om eindelijk
oen/aam en verlaten tu sterven. Was .'-iie ongeluk

kige liefde niet genoeg 'f
Haar nichtje Dom Clinton is het luii-iroodertje
van den beginne. Op haar iiohtiuniU1 Jaar houdt zij
al een preekje over de pliehten dor vrouw iu het !
Imwv'.ijk. veel te vvys voor een mei-je, dat nog met j
den hond walst. NVelnu z\j krygt een professor, |
maakt hom ge.ukkig en stieht vrede iu hot huis van l
liiiiir oudere zu.-ter. • ' j
De-ze zuster Kmmy heeft wel liefde maar leeit te j
veel roman.'. Het gevolg is.dat zij haar man on- i
huiselijk maakt. Tn.tiend is de tohüdering vanhaar ]
nalatigheid. Haar man. die waar»eh\iiilijk een zoo !
slordige kleermaker hail. dat aan x.ijn ja', waarmede !
hij nog naar een souper wilde gaan, reed --Benige k noopon
ontbraken, kan maar ter naiiwernootl van haar ge laan
Li'ijgcu. dat /ij er de luioopon aannaait. Niioit ivarmt
zij zijn paiitulfeU en dikwijls gelivtirl hot, dat zijn
thee koud. of, kan het erger V in lu: ijdn ••! nut
i/c~&gt;'t i-t. tïeeii wontler dat liot huwelijksgeluk
vorstoord wordt. Te laat xiet zij hare dwaling in. Ter
elfder ure gaat /.ij nog knoopeii on handjes aanzet

ten .,en ineitige berouwvone'u-aan rolt tlotu- do
.-cheiiiv» Viiii' hot Ihiuerigocd" des i'eleedigdeu
cchlgenonts; maar h-.r,\r berouw wordt niet eens opgonit-rkl.
Kers* na veel lijden komt de vjM-xucniug tot stand.
Tante Kiiphouua is een kwezel uit een bock; te
kwo/.ehu-htig.
(ïepi'ge li'.'hivr'is oen ruwe, n-aargoedhartige oom'
(oen looiiool-ooin.l llij stampt, hij kwakt zijn hoed
iu o.oii hoek", ..'4uat zitten met de gratie van een
boor," maar vet klaart dat hij ,aau hot grienen zou
geraakt zijn" bij het ziiigóu van uiolit .leanne.
. Deze per oneii doVn soms den lezer glimlaehon
i,ok waiir. tlo auteur bedooUle. da-t'men ernstig
Lykuu zou.
Ovoiigeus- Inil'le aan do auteur, di.o wel talont-hotft
en hot dien.tbaar trit'-lit te maken -aan de bevorde

ring van goeden .-maak en goedv'xcdi u.
'.-:. !o:i V'&gt;or!u."'l'd loo vmr coa Iv.igel-i-h j-tililiok te
(b. i-v, ii i.&gt;ii'i'.'i!'n ii. i-.-'i xijii'er'f;e!iei'koo--d.e.
pi'i^unau.-.-. ::.&gt;,iih';- xi:!i lo r.viui.i- gf.;.'veii te hohuon
i,-e!io'orl'ovent-Gai'i'ii'..-'.h'-i-.ior te I.oi,don zuil een nieuwe
(.per» opvoeren v.iii.ti.&lt;li4iii:uk -dj kuningin vau Saba"
T.li.'ii vei-ii-lile er i'i'eik-i franis vaa, en docoralief ..
eu eo-luui'-'» ziMtlen koning Siilonn' \\aardi'.' ;:iju.
l'lui -i'-ling ('i'li.er Uivain er 'tcgiMibèvel va» h'.ioger
liai.d, ll-.r zeil e.i:i toüte'iijk zijn bijl.ol-elie nainen
i,)i In-i tooucel ui' ie spü-Ueii 'i'ii i;ersii(,n':ii 'uit lift
ii;i'Ie te-'.i1.!..ent iiahdek-nd tüdoen opirtvieti .ip du
.|.'!:iid«ftl. M i-u i- ii'-.i bo;:ij; tle namen te viMaiul"ren
tn 'ie h:i:ul'.'ii:i^ in een ol ander ii:yTu:-ch O'i^ter-eh
land ie M.,).!jiii---n, &lt;,j'dat hot Ivigel-cli gnd-dienstig
gi.-vt)ül -zlt-h er ui-1, mt-iir aan. ergere.

,'lu een ].:i]i-is tv \enetie heeft men tweft hronz'.'ii
;;:IK , eu '.&lt;i:devt -,.1,1 \vomlprbarp fehiio]ihfid../H "tellen
i'.d'-i- t-eu p.nil.-r v in-, wa.irnp een Kaunoi'Sater zit.
.111 wuid: i'i.iiali M^hül Auïeio.tiicgr-ijhrevt'ii. M't'.hunc '
.'.-l-'i| hf! ,'le lint- liild tu rarij-'. hoel't ;:égekocht
toch n'tt

iu die ji!lli:j(&gt;
al t» geiifi',',1 zijn O'.il va» hun evonmr'n-cheii Vteads
liït nr !e te ''enken en te spreken. W;it'XOU(lo.n'Hij
Ze'.'gl-ll 't" , ' . . . -.'•..'.
..'vVjit'•i.'iiiiiii n v.\\ iinlers KC'frgi'n,.di!n (l:it lUj.nvan
eu vriKiv.''/ijl':!" i.i;'p Jeniiy tier, «on wat kunnen ze
om ook eip'-nlek Foiiclen!" voegde zij er han-tig on.
op ycrachl enden toon bij; rden1ct n van al die
men?rlier&gt; slè.t'hls nicirgiMi nog-'nnn • een arm Sc-lirji'-pl. dat
zij gisteren ol bedeu ojf hit» weg 011! moptfeii 't
Kbilltt'bartipt, koel vilk.... sleehis Iniu ei^eti'iolrtng drijft
ze voort: -.'ccliT'. il.'it doet hen in een kring
i'ontlloopen .... nltijn?' iüd-iizelfilt-n 'rin.?. .'.."•
Ken lniil gi-laeh. on g'-joc-l, een \yoe-f geschreeuw,
('oornieiigtl -met vldeksn eu goiNlasjot-jngeii, klonk
vnn hè! tu'schi'iitlek uit, en-de menigte stoof ('afiT
uit'-eii. Kr was tus-Hini een paar mannen pon si rijd
nitgi'burjtcn wie weel, waarover! on onverwijld
vcrmiie zich een dicht iiaueenge loien kring vnn
nipnsehen rondom di: twee bok-ei-&lt;,.die elkander bloedig
toetakelden.
Voort vau hier.... spoedig!" smeek!c Jenny
in doodnlijknii .-itig't, terwijl r.:j zich bij Ralfson aan

drong: ,o.- ats dln 'woodniidB mensclii'ii eens hierheen
kwamen.... en iln'ri blfiod.!... ik zou't bc^'M-ven,
al&lt; ik f\nt. aii-n mne:-t l"
Tn. niijll • h'iirt*', zeidH It-tlf-on. din thnns tot cou
besluit goko.nen wm; hier bened"U kan ik niet met
jp blijven, dat-H xker.. .. kom 'Jui luei;! Ik zal met,
den ka|jiti&gt;in spreken, rn inir&lt;chion \&lt;i er znll'i hier
nan boortl gele;;euhe.id om geschikte kleeren voor
je te krijtrcii".
«\\'al hen jn zorgvuldig voor mij!"
,,Maar kom uu spoedig mee,.., daarboven vind &gt;
Xieuwe L'itg-aveu:
Nieulaiis l!ejr-. i!r-«il&gt;' ui-iu:i-.ii &gt;.:&gt; n'-ii'&lt;!.!trt&gt;v!liüi&lt;l.
li-j.l'.-Vooriug op 'de.il edonk'lag der .Stichting van
do Lirei'htffho lluuyu&gt;cliool, -li Maal t'l.sTts.
.Mevrouw Kli&gt;c vau Calear. "&lt;i&gt;i-.\Hllr /&gt;ii&lt;lcti. Aan
de nage.daeht.cnii van niyiie Moed.T. Ovcrgcdrnkt
uit .Op de (.ireiizen van twee werelden"
l'iitur 'L'. M. l.'urci. X*o iji:.irltil!-:n lusm-ltni tin»
ll&lt; rlii/&lt;:ii titiii't CH (h) nbiili'riK, JLinl'rti-littiijiy. iCen
woord naar aanleiding van zijn terouideelde ineeiiin
om-rent de wereldlijke macht. IHt het Italiaausoh, .
door i', du'Du v.
11. C. lliirlnian .Iz. D*- liimfilt-lfikc.muxlit.n. \",c»o
plaatsulgku belast ingstudie, ii.iaraiinleuling der nieuwe
vei.-01'tioiiiiigou iu de (jouieentc (loeS;
Tyitaoü', (iuliallf.' Keu. Zang dua'tydüt'j
,luu Uuilaud. iVi/Wi; J/c)i»'-/tc«:.. '
liet April iiumjner van Ktflfti /fitnt'd hev.it .t); a.
(i. l'uruUeu,'//) lu-l-rifnlv iii-fliii-lit, novelle. Mr. Th.
11. •!•', van i;ieui.s.lyk. Uit tutitr Gi'lilci'scliu nrc/iii'f...
tiiugi-nphic van l'rol'. Kuenun. fci-H if'i;/ in (irqnf*
Alh'li- .l'red. Muller. ]&gt;.: AV'1.;"» "/' i&gt;«triotti:rii.-titi
in lïfi't. A. .1, Domcla Nieuwunhuis, tiiizi'
r&lt;ior.nitili'r.1 in il'ii r?i:i'i&gt;t:li'. l», van Ha-^eld, /e's i.i'i'.r
Spriii&gt;k.ii'it- l'. F. liruuings, /-.V« c'"W'/ in 't lulniii/
al ''.wat je jiooiiig mocht lioUrou". en. zondf r ceiiig
verder antv.oord van hïtar rif te wachten, iinm hij
de gi-liefde uuder den arm. en leidde haar langs de
smail» ga aft door .de m.icliini-kamei- tiaj'.r voren, «n
vandaar de kleine, trap op. die naarde hovenkiijuit
voert. . ... . .•
_Ópiiieiltelijk wns de opginvondonTieid, waarin
Jonvy- gerttaktp, toen zij daar vlak hij nn over de
werk-cililo. fj««en&lt;le. borrelende, op en 'neer fannde
madiiües piis^ocrcn moest. Va-t druklc zij zich tegen
'Itiilf-ou' iiiin, en Ibiistertle: ' ' ,.
Voort vnn hfer! vooj-l '••• • • 'h' hel! du hel!....
Vic, hoc hamert on ratelt dat daar beneden ! l?cd
mij, T'iin! tlii; ij/erén armen willen me grijpen!"
.•Maxr lievo ha ri ". zcide di' jonkinan glimlachende,
..heb je dan nog nooit van je, leven een stoommachine
ffflü'i'.'ji 'i' l|i« radci-en rn' armen i'uimcn immers geen
iliimibreei! VAU tic hun vool-pesehrnyen riehtiiijr
nfwijken: j? hel t 'volstrekt iijels te vreezen''.
.lènny antwoordde nie) s, maar vrrlioi'fl- liaar gelaat
tegen zw'n horst, to'dat xij de iiiachine.; Voorbij
woren en weer voorann bij den boeg ds vrijft luolit
konden inademen. Hier- rii-hite zij 't eerst haai1 blik
naar den linkeroever, maar die lag op verren
af';t(ind. O ik van den tegenoverliggende!) oever waren
-z;j ver genoeg verwijderd :: de boot voer oj) d« hier
zeer brcodu rivier nagenoeg in 't midden, 't Was
een duistnrênacht, rn nergens aan deir oever waa,'
.tumchen dn hoornen heen, ooh niaiir n lichtje te
zien. Hyenmin, ströomop- «f al'waart?, een andere
boot. Als opren ruime, donkere.zee.zwonrmen zijtla:ir
alleen,- op' den «ehielijk voorbijsehietenrlen ft room ...
en 'rondom lag water, wond, wïhlernip, zoover het
oog reikte. .
Kn toch hadden zij maareen ntnji tn doen, om-in
't- bereik te komen vau al dat comfort, van al dio
fjejiiükkeüjkhnion, die 'smen-ehen geest hnefl uitge

vonden, om do weelde zelfs over ik1 \voe&gt;tt'atrnojncn.
van 't \Veslen te dragen. Nog waa do Mik gevestigd
op het zooeven vcrlHlen land, mei zyn dooruige
tv/» ()((.-(« fijirttjliuunl. %llil i/fcrui tl r ij n lul
tlrovyiltih' ti' Auitifi'fdtiiH. Oiavutes nam- JÏHUIIO llóle,
Thoodoir de Kty-or, (.'h. U, olitis.-en en Gust. Doré.
lh' Aiii'itu in luii'i' I'IK'/.I» geeft i» de zet-de
atleverhijj: l&gt;t l'i'liifix, on hot vervolg van Cnunroit's
rt'ix ilnüi' Afrika.
Stntl«i&lt;Eüflif* on
.Naarmate de Oostersche kwestie weder de
aandaoht trekt, stelt men belang in de landen die er
geheel of gedeeltelijk bij betrokken zyu. Onder deze
is liriekenland zeker oei) vaa-ilie welke by den loop
der /.aken het ineejt geiuteresseerd z\ju.
tiriekenlanirs hevulking, in It-iii skrhts lili,(X»l
zielen, (of 15 per vierkante uiy], tcrwyl iielgii-er HU)
por viorUante inyl teil) is blijkens de laatste, volks

telling iu It^TO tot l,'.h&amp;,ü7,S inwoners geklommen,
mituurlyk zyn hier de. a^'/ilüvan du JonUehe
eilandeu, die er sedert l^b'3 bij lohoortu, niet
niedcgerekeiid. Dijt met. deze ook handel en nyverhoid
iign toegenomim bewij/en de eijfers van uitvoer en
boliuitiug. Do 'krenten, hot vuoi-üaam.-tu
uitvoer-nrtikel, bedroeg voor tien oorlog nooit meer dan 10
ujillioou pond, in i&gt;7l IMS millioen, hetgeen een waarde
van ;!,"&gt; millioon francs vertegenwoordigt.
He wijncultuur is in dio jaren twiiitigi.mal grootcr
gewt-rden. de granen zijn in hocxeelheid verdubbeld,
i» waarde verdrieilnbbeld ; de opbrengst van tabak
is vijfmaal grooter geworden, olijven, vijgen en
luoerbcziëii werden eerst laat artikelen van uitvoer;
de katoen die men eerst in den Amorikaanschen
oorlog hegiiiiiien is te k wecken, brengt reeds voor
11 millioeu drachmen 'sjaars op.
De veestapel, 2,3&lt;)0,00&lt;) geiten worden gehouden bij
gebrek aan iets beters, want de grond is zeer onge

lijk iu vruchtbaarheid, zooald we reeds uit onze
Uric'.sche antiquiteiten weten. De industrie echter eu
vooral het mijawiv.en kunnen gruote uitkomsten
geven, men U echter slechts sedert kort begonnen
ze dueluia ig te exploiteeieii. ('hromium, lood,
koper, ijzer, mangaan t n zwavel wolden te voorschijn
gebracht, het klassieke I.aui-ioii bracht iu 1S73 ")
millioen dradimen op. Hot oude l'aros en
l'enthelikoslunriiK-r vyordt op groote schaal naar het Westen
uitgevoerd. • '
De kt)H|ivnarduvloot is van 1-Slt» tot 1874 toege

nomen van li»*l schepen niet lXlillÜ.ton inhoud, tot
;"iH3H met ^l&gt;U,7l»ll ton. • . .•
Do handel echter heeft den groot «ten vooruitgang
veiUnmd. In het jaar 184"&gt; waren de cijfers van
ineii uitvoer •&gt;L'.»)'MI(«I en 11,I»IO,IXH&gt; drachmen, in lt&lt;7:!
Hogen ze tut 117,til:?,102 en 7(i..'«riM.n.'!3 drachmen. De
nationale bank, te Athene gevestigd, met l!»
filiaalbankon, had in I.s7li een ouizet vi"i 137.lll.ti37
draehmon.

tiet l'oiisisforie van IJrandünburg heeft
gecoiutateord dat in het vorige . jaar te Oerlijn van de lO.Oml
kiiuk-rt'ii er (itx&gt;l) ongedoopt «eilieven zijn. terwijl van
de hinvelyken er slechts een tierde korke.'jk werd
inVun de biuiienzobè'n iu Kurupa heelt de Aehen«ee
iii T v tol de grootste diepte, op sommige punten is
dit meer l'l'l mater diep. liet meer vnn Constnn?. is
iiergous dieper dau 300 meter, het moer van Chiem
111. dat va» \Yalolien l SS meter. Duiten Europa zijn
er diepere moren. I»c lÏJO.io zee iu l'alestina is li.'i
meter diep. diianMiboven ligt, h.i u- spiegel IJ.» moter
beneden de opperUakto doi' 'iliddoland-clie zee.
zoodat dit eone verzakking van den grond van !»!M
meter-- geelt. Het meer van Tibeiiai i- nergens meer
dau t* ni'-'toi' diep. In Aitiati-ch Uu-land echter is een
moer, hot Daikal meer. dut e'ene ont:iet'.ende diepte
heeft. Men heelt gemeten tot 3(U7 meter waar ech

ter de bodoin nog steedi dalende w-.i-, zoodat men
berekent dat meil mimteii.i lot 37(iO meter komen
moot. terwijl de grootste diepte der Middellandsch
zat. slechts ^U'7 meter bedraagt.

De work.-takiiig onder de Londcn-chc metselanrs
heel'! in het goiieel '-&gt;'2 weken geduuril en aan het
comitéter ondersteuning ongeveer 30,1100 pond, dus
.•ili(l,(«H) gulden gekost.

Hot Kabinet t; Washinglon heeft jilan tle
niogcndhedc'ii uitteno'ódigeii een congre-i ie orgaliiseerenovci'
de munt kwestie en. wel speciaal tot algem°eue invoe

ring van don dubbelen standaard.

De Russische regoering heeft ecilo pom van
li;rniliioen roebel* aangewe/eu tot ondersteuning van do
l,inueiiland«rhe niach.iiieüfahricttié, om ziuh onafhan

kelijk te uiakcii vuil het, biiiteidand.
mo;rtt'f{roi'(loii, met zijn rii-tmoerassen, door lagunen
en van alligator-: weineleiule «bjiyóiis" ibiorkruist:
op g'n Isehu hoo'.'le loerde mis "hien e-m. panter
tmder het dichte ionhner. en keek vi&gt;i-hait-:il de boot
achtcrilii, of wa-.i misschien een l.-eer naar 't water
atgedaall, om zijn dorst te le^-ehen : en hier., .een
' breedc, pvachtigo salon, welks muren tellier geheel
uit s hihlerijon en spiegelschijve bestondeiij met
zvvaaion'le kroonluchters a.iu de zolde:iiig, blinkende
mahc, niehóuten tiifols in liet nndden, niet llUwecl
boklccdc fauteuils en ottonianos lanr,'s de muren....
gordijnen van zijde en zwnre wollen stofïeii, tapijieii.
op'(len vloot', en opgqii'onkto Iieeren in hot salon.—'
En daar trad' nu Jenny hlhusn met haar grove
lnti:kjfö*ifWwi«/&gt;Vkl.-.cdij ei met den ouden «frou.hoed-.op
het lolckig hooi'dju ! Of zij ook hucfdn ! ,Mftt kracht
"riioest zij zkli aan lïalfrnn's arm vn-thouden,orn niet
moedeloos terug to deinzen, cu schuw trachttezüzich
achter hem voor do 'blikken der aanwezigen to ver

schuilen. •
lUII'son intiis?chen, die• mot de gebruiken aan boord
dezer stoomboot reeds bekend was, vraagde
onverwyld naar ili-n' elcrl; of ?&lt;&gt;cre:nvfc der boot, om 't
alicicerst Kijn p sxago'te tietalen en zich van behoor

lijke plaatsen voor zich en Jenny te verzekeren.
Waar zyt ffij aan boord gekomen, SirV" vroeff.ile
man hem nogal yefwondt-rd : rik heb u tötdusTcrre
nog niet graten'1.
-Aan délaatste aanleg|ilaat?. waar RU hout heht;
ingeladen". • • •
• •„liiilrtol'?.'.'... en deze .jonkman ook?'1
- -Ia".. ..•.'..'
•nlu do kajuit? en waarheen 'f. ,' • •
Ia .... naar ('nïro !" .
..Voor heiden?" ,
Xïkcr.... innnr voor mijn metgezel in de dames"
kajuit".
("IV'onH ccrrolyd,)
De hoogste» punten in de Vereoingile State» vun
Nourd-Auierika xiju (iiays-l'eak die 4.'i7i,
MountTyndi'.H die b&gt;li on Mouiit-Whitney die Iö7"&gt;meters
bereiken in hot Miocuwyebergte, terwijl het
rot?gcbeigle den Mouiit-Itainier niet l Uil en (irays-l'eak
mot 43Ï2 meters hoogte bevat. Onder de steden ligt
Georgetown iu L'olorado a&amp;o'S nieters, Colonulo-City
1034, Houlder 1I&gt;17 en (Marron-City 1439 meters ho

ven den spiegel der zee. Dat het eiland Oarrignton
in den staat Utah 1-lw) moter hoog ligl, is
begj-ypelyk, wanneer uien weet dut de bodem van het
(IrootXoiituicer waaruit het m-h vei-lu-ft, zolf li'Sti meter
boven do oppervlakte der zee ligt.
der ll'cck.
l
AMSTERDAM.

Koffie. i)e handel was zeer traag en' kooplust werd
behcerscht door ile ongnnatigu politiek, de maikt
sluit flauw.
l)e afdoeningen alhier in de ofrste hand bestonden
deze week uit de volgende partijen:
•2M bu. Mala.ug ex Antoiiin.
187 ) , , ,, ,. ,. l Cntlii:riiie
" ' Palciiibans Dali en divers ex '
l C».
terwijl te Hotterdam werden afgedaan
!t±s bn. Afrika ex Xtirtimin.li/i:
SWt , Java |
4SS l'alembang i tx (.linnin.
!(&gt;!&gt; , Samaran"
lö() Soekaratlja ex l'rina Hendrik.
Thee. De op .'t tlc/.er ulhier gt-hoiulcii veiling
liep af als volgt:
~3 J 4 t -t J -J J l l ! 1 3 l J y ! *^
• - i^-=?i = l"-i- ?- r.'
• •iii-ir-ï-o--"
- H _ i: S - " 'é= •" M ?. i: 'I ii = T
'.'SI l
De bij iu.'-ohrijviiig .'langcbodvn l'il) p tkkeu Turksch
bl.-ve» uiivt'rkt&gt;."ht. \t&gt;ortaatl hetk-u:
f")J!) paKkeu Java.
TTÜli , Sm.iatrn.
HV^s ve.tcii Miuehind en Sonborn.
i*&gt; ., Keiitiiiky en Virginic.
,'itMH) balen Ouat-Indiiich.
*iO i-croon. Cui'aeao.
Katoen. Hierin had gedurende den loop tier week
geene verandering plaats, de Mciiimiiig bleef va-t
doch allee» wertl voor la-hoeftu gekocht, l.oeo
partijen hruehtun dieineiigevolge betert! prijzen op
dan le^eiing.sli.'iniijiKii. lu nu.st-Indi.-eli werd weinig
gedaan. De notceiing is al.i volgt:
l.oeo good Middlinr; 3-1 cent,
- il- i ^
luw Ji l' •* .
Aprilk'vering basis nii'ldliiig iiuhn 31: l cent.
Mei 31:1.
(iood fair Omru per ritoombout 2^'i
fair Sept. (K-t. , 2") ,
Rijst. Ongepolde. Afgcdami werden ItÜÓ balen Uoetlhe
Hndjii Tafelrij-t ex KI rshtrr/cn, tot f 1(); i hy de Netlcrl.
Ilaiidel-Mnitlsehuppij. De hij inschrijving aangeboden
li-Tfïbuien Java Tafebijst per \onill l" werden niet
gegund, doch werden later van tleze partij pi. m.
•KXJO hu. Kaïiibnighauer grontendee'is voor e.S|oit
vt-rJtticht. liurniah-ooitcn blijven bfecds in willige
stcuiluing vei keoren, tengevolge \'aii de .-toeJs vooruitgaande
]irijzeii op do IlI'vuiTplaatsrn. \ooi- hier itrriveerden
per f.il-i i'itiil S(,'-0 bu. Java Tai'elrijst die upgi-slagen
zulle» worden; voor de l'ullerij lüiil tons Japan.per
Sir \\'illiniM \\~itllnii eu aal: de Maa.s 11751) balen
nieuwe Ivingoon (er •Inlnir. (ïcpeldi1. De .-toinniing
blyft wiliig eu xiju tlu ortlors op tle verhoogde prijzen
fc'eed- vrij b^lungrijk. Vooral vour Japansoorten be

stond vet-1 vraag, znouel in de tmiii:airc als beste
ooitei:.
Spscoi-ijcn. Xnleii. hl tïe/o week was do s'einniing
iets va-ti'i-, iif'jedaan bij inschrijving tloor tle Neder!.
llaudel-Mantschappii -l'l vn. en :i."i kn. ex Vinirtn'iir!*,
Vnelio. De .steiuuiing vnor dit artikel was zeel' Hauvu
bij inschrijving werden door tle Nedcrl.
llantk-1Ma;it&gt;criappij vt-r!;uclit !' vn. e;i ku. es A'/i'Kü'i1
H'i.li:rm-i/. Xagelen. ll'ieriu ging niets om. l'ener.
Hiervan vonden fjei-lie a:'i!uoiiingi-ii j laats ui i-
tk.sleiaiiiiug /eer kalm.
Drogsrijen. Diiidro!,in" blijf' lanT iu ju'ij- evt-nw.el
met redelijk gooden a'/.ot. Dikke l!'jtt-iiig v.'ci'iig
begeerd, maar dunne Kottiiiy en •Maiidemalicr.'! lüet
meer ^t-viiia^d. Meii noicert ba-is ..muoi t-n go' d
vau kleur veerkrachtig, Weinig .ichaile"
lïaiijerina-sing en jiiic-o . ... f |fi a II
l'.nlung ..'....	!l . l'n
1'assir. . . . . . ,	U .. l l
Koelie du'i .' . . . . . . . ... •- 'J
i ?• « i y. K- -j- i?,
Sjiker. Ten gevolge vnn b'gere nuteeriiigen op de
KngeUuhe e.n l-'iaiisclie niarkteh, v/il-" de
-tonniiin;;deze week bepaaldelijk llanw i'it ]irijf.(&gt;ii laser,
(ierafiineerd werd lager tiangolioden en retireerdt-n zi'-h
koopers hoc langer hoo moer. De politieke toe-taud
maakte dan ook dat do iukoojien j-L-h tot het hoogst
noodigc voor raiiiuaderij be|iaaldon.
De op. l dezer opgemaakte waiii'dBverhotiding vau
.lava Suiker zoude zich dan ook hellen niet meer
kunnen handhaven, namelijk: .
N", fl. l 2ls 'i togen f 11» JaiiUr.riwaardo.
i).
ld,
11.
l'.'.
11. .. :-!ii"' i
. •• , 'in. 'ai
.'. Ui. ."l'i
17. :u . , :ür
., 18. .»»'•.„.- WV - . .
. ..l'.l. Ki'i . -• :i
. 2t&gt;: B.:-!l' - , :-:3:a '
.•Van vcrkoo|ien Kunnen wij du vulgrinlu Iranfactii'n
melden:
7lükr. Sonrabaya ex .l'urncl/r; Siuif zee m f., u". l^i-&gt;,
goed en zeer g«etl, pr(js geheim v',m boord.
Kil _ Saniarang, ex Ai'iibiii, 11°. 11, kwaliteit zoer
. goed, f iS'!'i opgeslagen.
'•lüti. - - Samaraiig. ex GrifCii, n°. J"&gt;. kwaliteit goed
en zeer goed, f Drs opge-lagen.
Wil Saniarang, cx\Ai&gt;i-&lt;l?rtli&lt;i&gt;i, n". K', kwaliteit,
zeer goed poiiimiga vochiig, f 3i oj&gt;gesl:ig&lt; n.
20;i n Saniarang, ex JfKrm'"", n". IU, kwaliteit zeer
•• gocit, f '.ïopsealagéu. '
3110 I'röholingo. ex liittivlifffil., u". 13, kwaliteit
: -zeer goed. f 30U opgeslagen.
4117 fjiimai'aiig, nx Ctt/hu/ut, zee mr. u". IL" j,
kwalitoit, goed nkel vochtig, f .^'.)|;., zeilend.
lli . Soiirahayn,.cx 'Xir.nliilr, zee m&gt;. tf. 11,
kwa' " liteit, zcer'gf&gt;ed, p'rjii geheim vau boord.
l).e jirijzcn van gerafimcerd kuniiuh wonleu
aiiiigciiomen tot f 81-vi, f 3:2 op tormijn.
l)o aanvoeren van Juva Suiker bedroBgon:
Kcd. lland.-M11. 1--7S ri,i!S2 kr. teg. •.'.(Jij) kv. 1H77
Particulieren , 1WUÜKI'.. . . -«.V-W - --'
- Totaal iyï« llili,t)sl kr. tejt. Kf(,:;,SK kr. bs77
Voori;aa&lt;l Juva Suiker: .
;5Ced. HiimLr'MürvS()0 kr'. tcg. -r- kr. 1877
I'nrticulicren', . . . . 73,:l(i7 • .„,.lJ,13t'.
(iiirontalu .	IO 11
l'aarlmuer,' Maoas-ar Aroi1'. afgodaAti weiden IJ pi.-.
ex Clifin'ii'i' to' 'i&lt;ngeve"r .1'MI». SohÜtlp.-d. Maea-sar
niet redt-iijk gooien a!&gt;et. ( mede .-orieeri.Mjcu rotctit
men pi. m. f 11.—tfuni Dam.ir aiiiv g.'--l'.uid t n
prijzen dalende. IITII t'upal. urnen Hard de veiling
lii-p als vol:;* .if:
lii! ki-teu circa liii.iüi kilo van t' In tot i':;',i vevk.
&gt;':&gt; korii'ii .. l-V K a &gt; .. .. . l.V; .. .. :;.»• .
lul balen .. L'T.iiil'l .. ,. .. &gt;- t .. .. 11 j .. '
:'.|n ki-ion .. '".".nnl	&gt; . _ u
111-s balen .. Ii.". .11:11), _ .. '.. ."i1,, ... 7
Xin'lite ('npal mot zeer weinig voorraad on ziaulo
ze'ü's i' l'i j Ie iiLiki-n 'x\',i\. (iutta reniia. .K.-iu
Maerts-ar 17(1 e. A f v, -jjkel.d luie:. lï;iii-. llaiiea's
!»o c,, lim' e. .Sninarra "n e., uil e. ]:•_•!.„il, ,| j:i ,...
tin c. l)'1 vu iriiiud i- zeer klein eu vr htoi-rrht veel
vrai'g. l'.i.-'siu•• Vora ilauu, i-n alleen iot in.'.Mue.n
prijs (e pb.ütsen. Men imte-ii L!"r e. v&lt;ior diHi
prima 1'iid.iu^. l'a«-ii 't'iinor v. oi-tli' jiev'i'.'ia^d ;or •
.cl1, ca i- i.'iit-. . ,l;:v.i Kii;a. I'l.-i'Xan i- de voorrau '.
bijna gi'hcel• opiioruim.l cu i- er'tot hoogu p; ij/.e»
vél vraa -. J.i'va Kamfer .lamv gè-ti-nitl,
nuteoririgen f ."'l i... ."&gt;J e. .Japan Wa-. lïicii» giiüi nie'sonj.
-VerfwaibR. Java Imiigó. tn.tle afgcloopeii weel;
werd f'echts ::eer weinig omgezet. Verlhonion. Op
lli April komen te lïuttei-daut in '.'eilriiü1 cirea IMi.inni
kilo Ueelh.nit ai'koiii tig vau hi-i seliiji Ai'ii;':ii. min'
of meer beschadigd. Ditidivi. Van tlit artikel kom,-u.
12 tlexer in Veiïilig to li .it',!?rdaui eiréa 1's:.,"^»! i;il,i
min 'of'meer be-oh'i'iigd gned e-, Afii'liu. eu ;:iju \aii
de diver-e partijen per .'-V //,-/ anngevuol-tl. liühalf»
aan boord tot va-to 'prij/cn afgedaan, lliir.-t.
Aiueii• kaaiische ouveiandonl. ''l'cqientijiKilii!. J.oeii goed
Vturdt lager-aaimeljodcn, wu'nrdour in tliv.o . week
eonige oniiiet tingen voor o:-.[iort p hint s. vonden.
Vruchten. l&gt;o vi aa f n.'iai- Krenten was ,lé;;e v/eek vrij
gruot, doch de-tiic-t ir.m'ii&gt;t;;itnde kv.aiiien slecliis ;:e,.r
weinig omzettingen va» eoiii.'^e het.cekeiits.tot ::taiul.
Granen. Tai-he xoinler handt l, op levoiiny Nuv.
f ;;^7. .lioggi;. onveraii'lerd: jarige- (ialatz l' Jlo.
Taganri'g f 'JU.'!, 2n."'. NiL'iiwo l''eter:-bur..er f l'.'^!,'
lü.'i, jaiigo dito f l'-"!, a comptaiit zmidor k-n'tiug
]icr il'»'» kilo: op ioveriug per Mei f I'.ij, p.M,' li.i),
'•1M&gt;, Ootulficr f -l :!&gt;,. m lil'S 1!&gt;7., '
Oiiezjflen en CMsü. I.üiixaul. I'iij/:,-!! Kleven•
onveiaiidord bij urte sictuiiiing. oo'io pi'rt(j
lllili:-! ii' eval werd' !oi f '.'&lt;•* per iMUIl kilo tv!;.au,
.Koo!;:a-'.d t.;v H"»,ki!o'olie April f-H'.» per L'OUI kilo.
l •' . 'n 'f ' • •• &lt;&gt;etob.„Hl.", •„'.,'
Lijnolie met. eenigon hatulcl i'ai-.w gi'stemd.
Totaal 7U,iri7 kr. teff. 12,134 kr. 1*77
De voorraad Ruve Suiker in do Nc
orlandscheJ'Jiit.repóts bestond op l April uit: .
bS78 .3SVh&gt;j,03;! kilo tegen lQ,ii2('i,371. kilo in 1877.
Tabak! Javii soort. De afdoeningen in deze weck
uit de eerste hand bepaalden zieh tot:
Hij inschrijving Hi(» pn. Vl&lt; ex l-'.mtnn.
In veiling 7f&lt;0 KoelöndMöph.blèv.bnvèrk.)
In Suniatra soorten ging niets om. In
Amerikaanfiche soorten werd veel oil.'gczet. Verkocht-wprden:
431 vaten Marylnhd.
2.2- Kcntue.ky en Muson County.
i)e aanvoeren bcelouden uit:
l»07 vaten Jlaryland per /Vcc.-osrt.
• 13 •'„' Mas-on County M ' .
-15 n Marylanil ., (JoiistiinrC.
Ansjovis. Ii! of hij vo ir! lm ing z'jirler zakeu en
zijn do ['rijzen dan ook gein el noniiii uil
l--,"7 v.tir,' t /' l •"&gt;
!N7&lt;i ' , 17'i j
IS.'i 17 ;
Tin. lu navolging dor sV!-i!-- l,r,', r alkmii	'e ;
l-jigtlsche iiütc-ei iugi-ii is (Ui/.(; tiiim.-&gt;rkt ook lla r./
ge teiutl. Loco limika wt-nl t-.-rsi i"t f l'l en la er '
tot f H'.i'i iifgi'gttven en i- thans niet meer dan
laatstgitiioeuKk' pi ij' te !«ui.'.-'.-ii, ti-rwijl tut «v-r
lgenoemde J.rijs tu kutiji blijl't. \ uur !»:liiton In .-tt-'-ddt;
men f J* eli wordt d.iar.o» ver,k-r u i'i," budeu. 'l u'
f371',', wellicKt f y7'!« zijn er thans koopcrc.
Fijne Houtwaren. \Vni-lclhout met •/.;• r urt-M'v
i voorraden. Men noteert ci.'ca l 7. Sandelhout,
llierI voor bestaat veel vra:'.g en zonde circa f ) te
maken zijn. . j
ROTTERDAM. - '

Koffie. De sli.-miiiii.g bleef bij voortduring godr'.ikl '
! e» zijn ]irijzen ints lager. A'geJ.-1-.iii werden in ,
: eerste Intnd.
\ 771 balen Pak-iubaih; en Java ex llniir'it. ;
i l lii , Ja-.a ., i
l.'o Sin,.kar,iilj:i l'i'.ns Hfiulrlti.
i'l'-S ,, Afrika _ \nruiim&lt;!ii.
: Tabak. Hiervan wire.uii bij insclirijvii.-g afgedaan:
ii&gt;) p.ikk- Java hoofdiii. Wiiehmiin eigen Aaiiplunt.
^7S , . n ?! Tempo.
!''•' n « -, \\ •
ll.v.1 , .. .. VIJL Krus-ok. '
:-li"J .. . . VDL K.
' l'.Ml •_ .. .. Ta wang ocljo t'uit r. Mi.;. :
tiiiö_ Sipuatra ., l', v, d. A,.

te; wijl in^fïalili'. k" vciüiii.' keepers voiitlen: !
•i"-!]-ak.lava'lildui. \\I1 Muhnii.' l'l - a M', r-'.
li". .. , . l'A M 11 _ li' _ •
^ r l'A TI! Iü_—..
l	K\V M l-j!j.li" ,
i:;ii , _ . M,l D 11 ,17 , .
M . . - lui T H i».i'j , ;

l'.Hi '. .. Kee.io a-.ieKSAL.'.C'.iJ j '-i:,': _
uit tk' knul wenlen buitel.d.en vorkooht;
' l'l i va'eu Marvla'itl ex &gt;'• i«i.'it„iii. ..
l!1' ., _ . l li-i ni:. i

Suiker. In t(",'...u-teliinginot tle betere t.o'in dij iu
. tle lam-te b.'ll't v,ui Maart 'hoersehte, was 1. t artikel
gedureinic dn af-e!""|-ene v.r.'k weder z--er liauw '
'&lt;•-teiiid. t' -ii-i':.iieeid wen! meer ani:Lfbode:i eu l ,j
i;el rek-.' v:;» g;"idt-L'zamo ko'.&gt;p''!-t x.iju de prij;'.-ii
van li'uwo -uil-itr i't- k.uer. Aptilwaaide i- 'ian 'juk
niet nieer te bvilim;,.!! eu lw.ii.crs zijn ong-.-n'-sen 01:1
t'jt t' l uu,'ur Aj:&gt;ii af te iloeii. De vuurraitd van
lluwo ^itilier in do Nul. Ki:1 repu's besiund bl Maart
uit:'.
Am.-'erd nu JJ.!("-.7ii'l Kg. te.v-n T.i1 .7.Vi K-.1

.':','..!"'!.&lt; -"- K_'. toL-en in.."c"i'.."71 K.'.
Kaioan. (Jiiv.-ruiiiit-rd. A-.iioiik. «p Lsvoriiig li-
•''
Ameiikanii'cii -'ilkt n:i Idlintf I'.:! eei.t.
Tin:ieve!'y t.'.1 ••! ' • '•'"&gt;
Spccerijsn. l'e •...;' •* -'..';;! d"i r (^e N. ii, M. lij
in-''!iiïj\ iii'_' r.-ui1.'''. r-'!' i; ~ -'i, i:, al; N,;^r«'''. i; e'. .^/ •''
y.-(Y'!cll tii'.-i s.'.^ini.i.
• 'VoD'naad en A.'-.i'i in .-• i'. . ' '
Kinde 3In.ii: i&gt;7--.
. VooV". (V !'•.'&lt; l llnvdl;.
Ai'evoi'. M;;:'!r. •

i-&gt; 1-77, 'r 7. i
Nulen. Ivi') lul.l'-i '.'•.'•"
tii'u'eii. Meel;v.i[i niet invr lianlel, jirHieii. cclücr
i'iiuw. I)&lt;ii(iiii7o lüaiifvln'iit . i; 'tut l ;l'&lt; te knop.
("Ijl 1^ deiler 'ki.nien ;i/iii.'l' ili \;.Ü:L: rin.i ^- ..";! 1 1 K^.
!&gt;i\iiiivi on -ii-ca.' ^I.IMI KL,'. (uyMmut. n!.Ie;; meer v{
tuinder d&lt;»'&gt;r -evi'.iter •! e-eli:uiii;ii. Tèi'i eu'ijn. Hier

van .werden li»i vat,.,;, ju -1,^,, j,,f (. ].;', ai'.;(.,].j:,'u.
Il.iVft wiin.lt tut f li' - 'e koop aaiiL'eNii-ien.
Granen. In heV !;e^ia M'::er wei-k ^ijn de prij/eii
vuur ui!" seurten teii-'eVdl^-e der onni-'lürenilt* pi'li-.
tieke l'eri.'liti-n ;;i'-: '•_..'. i!i" il 't-dvit V"rj;,'i;ii.' v. edfnnn
iet&lt; jie/.akt. Van il : b!ii;eii!,u:d .kw-anien &gt;leèli?&lt;ver-r
weinig rtaiii'ii'diiiitei!. i»u X'.ii^'ejide fii'u'oèninuuti
v«niden ailiiev |da.i!«.. • .. • ' •
Tarwe ji'. -l|k' !;». l i' l'.'n u' &gt;;ixirifj!i;i . l':!:'..V
_ _ .. lili KM _ C.ileiitta . ;.f:ys ..-:;:;ii
_' ... ., lii!l i.il ..Anierik.sTise. - :\.',&lt;\
'Vlii^-eud
Mei . -,-'.'. .• .
. ,'Juui-Allg.U.-.!ll :' . .'
Sepleiiiber-Dcccuib. r
[{•'.sipolk* zoutier zaken.
*' Vliegend ....
f HU
, ;;i:-.;:i',
:ii:, :;( ,
.» ;;l V ' •

f-UU
•H»
Sopt embcr-L'ci-eiiib'.'i1 .
l;uapkoeken f llll, f H'). '- .
.' Lijiikt'ekeh.Z.K. h. rtle t 11. f IU..
. • n • r, iiiurine •„\'2, 11. . • ' "
. FiUroleum. . l h, su'inmiug was d,-zc ,woek v r y vast,
doch was de omzet vrij o.nhchingrijk. Men noieert:
Lo'ei. f IS! i Sepf. f II';. Sept. De;:, f 11: ,.'
Voorraad i» du'volgende liiivi1»--, wa.-u'by zoowel lüco
als zeilend en in lading. .
Voorraad. ;
rjrenieh . . . 37rt.lHrJ vtn.
Antwerpen . 177, |f*J. ,
llambui-g . . l!',óJ!&gt; ,
Uottcrtbin. . :ii,llln ,
Aih.-tc-rdam . 'J!."K!7 . •
.
n _ . I-."' l--"i. S:ixi&gt;n.-lcn. . :&lt;:i l
••'•'. .• .. lli'.' J.vi„Ói!eiittaCliil&gt;
' " ' . &gt;n.&gt;. 2 . . . -aü'V . :):r&gt;
Uoir^e. illil l .. Odcs-;i j&gt;or«.i.vc: M'ac'it
v. a. j!. ........ U' s i
. ». .. -• Ainoiik. \\e 'ern
jfi-il• . s.'liiji yei'w. v. ;i. 1). . . ijiCi • _:^&gt;7
•'.'». lli^'.l ir Nurtiierii . . .. ^v.-j _ 0.1;,
• , . . Ili7.^_ , ••' . .„-JiD H^j
., .. , We^tein iiiN.-Yolklad •,$*&gt; -1»!
, •. l l ' *&gt; U' !!o&gt;toeker.. . ^10
:. n ., n H" l!', iijrftiiro»'. . li!7
' ', ._ ' l lli 17 , Suratow . ' . .. -2ivt .,311'
' • '„. 117 is i lV!or.'.l&gt;nrfjpi;..'B Isc» ^-17
• . , H « '"do&gt; a jier si.
onder• WÓ'lf llij |';lHij V. .'I.I!. '•
fier-t . lü.'iO . llll llij u-()de-.«i . . ]t
llaverp. 1(X&gt; 7li NI ..(iiland.tlivoer,
'
]!rs'
n 17Ï1
.11

«'.»-A [leveringen.
Itrcinpn . .vl l.üo:! vtn.
Ii,n7;!
-.'.lm! fl
1,S7S '
l.'.'fil'
Antwerpen
Hamburg .
Koltei'dam.
.Amsterdam
Totaal l!„r&gt;,7-l)' Va!cn. . Ai,ïi2( \ln.
, ' Uitvoer uil alle havens v:iri Xooid-Amt-rika to-f op
2:'. Maart in 1n"«, :-iii,!iiri..VJn Cial.,'teKvji i:;.nj|.&lt;Ci| ti»l
in 1877. .
Hennep. Het eonige, veriucldiii'/sv.-annügi' .«reilurendc'
dCüO wenk is de veikoO|&gt; vau Italiaaii-eli'- mei k I'.C.
tot /'NI. Deze week werden aangevoerd KÜ) liondcn
Hoiigani-sclic die lot f 't.', te koop fijn.
\
,'Mais n. f , AtlieiiLaau chp ... i,-s
. fl' '. • dito (lagelijksverw.
j. v. a.' I!. . . 770
l lloekwèit p. l(l&lt;)ko.Noi'rd-I&gt;rabaiitsehc -""'
: . ., - , n Lilm.u • . . - . I7J _ 17'v
; ... . ., 'r ' UU iu."i u'
Kouigs: beiger v', n. l'. . , 177'.'j
Potro'eum blijft vast "es-tcnul. (ironie, partyen lot-o
we'rdeil tot f i:'r'-„algeilaan en blijl't op deze prijs
kooplust, doch hoinléiN ui t geiiege» lager d'an Vol
f i:t''j ai to geve». :&gt;OI vale» per (M.ohor wenlcn
tot. l !" i V("'!;oeh&gt;.
Ccnavar lloll, l'roel'f 1U';. Amst. J'roet', f 17 :i.
Vlas. liïde af,'eloo[it-li week was de stemming
roilclijk levendig, vuur:.'! in de btóeu: slerke soorten.
A.iugevoerd worden iljtiio sti rn meest af» ijkelitle kwal.
waai vo r hfogc prijzen gevraagd werden, uaardoor
de xti'.en belcuinierd weid.'ii. Tnch kwamen eeniL'e,
vei -koiij; 'ii ti,t si.üid. -M. n nol eert: (imiieen 1H-I7 .-I.
;r"-d v»!'-! u 17-!- -•.. m'd.lel !U-.".L' sf, ffted middel
:".-''':"• s', l.e-l "i Mill .-t., ii;&gt;i en cxtl-rt lijn lü-il") t.,
C.ilai't.'J, :i A;i-.'l. 1'T!'1. ..r.1. K-.!.-.v \ /..r , v;.',rl ir at f.iir
ll;' »•* IJÉ«,1(J .1 IU-. l) • l, ...l l iüil.l :n t.!.i l - . l t /')&gt;! ^'&gt;' »l :.!s 't. L
Pi-il!..' M, ,,',1'üI. l ..7 .l- ,'. i. f. lii il.- k..;ili lua- iMn.l".:.
S-.:, .(h lu^ik.'ii L l » 7 '5- c. i. l'. vi:i tic K. i'jt nurtr l.'i:!.J' t. y.:i.l- n.
l ji,/,iL.I i;,,jj l. ir !'.,,'« l!,. l.U. i,fil:.,;,ir II,, l, s.
!: •;/'•'! - . - , t -, » ,. 4.7.
liij.t. N:i-uiv olltt/. i-u! • T'.vl- lts. 4,1!. li.i'.l.iul 11,. 3. 13. Si-ii
11. k. l .1 •:'.::, (i.i.j-i C 2.15- c. i. l'. |i r .t'j.):u'i'«,l &gt;••. im.l.i
().;'•&gt;•'• *, :ï. c. i. l', (i.'i- r-fnuriii.c.t. l'j-ij/.'it /i^u piii..! tr.m
n,-\. -S: • j,-!, r .&lt; j'. I. riVj.Ui' K». 7. t. \rjlilra i.mr l icij.'ii
&gt;i.i K:.)i :il, JiiU' Ii7 'i. X:i'li-n t"-, vi:l il- h:ia|&gt;, Jlitc l'l-,
TJI-.M: i'j'-. -K..ilcu l") -. Y.:if ililiiji.,', Ji.te S7 (i. S..nr Si «-Vurk
S O'j. K'&gt; IV u ji l,,:i.l&lt;jii (i in. llü!ik[&gt;:i|&gt;i' r l 'l'.. Jn'i.ija
(.T'.li'ti'ii l Cl ,. (J|. l'::iij&lt; 3 in. il.)i'i:ni UMI tti-s. .Ï3.
Liverpoül, li .\in-il. 'lYr 'IVlc.T.) Katoon -tMnnii:i#
heil 'ii b'*.ir. Vcrk' ..tl vrui :l&lt; n dr-/ S'/"1) !)ii'. lL&gt;V'*cr 1'i'riO Ijii.
( &gt;
J. '
Illiu' r lier Wrrk ^1,0'JU
VI,.,IT;I .il h. .Lu 7.Jt',l/.H
Wi'i-k'. l.jki- iiin.j.r D.'i'.'n
". ,\;..v!. l ,v .,T va» l.jii'ilii- -';•! t .:i. Vii',iTfi.nl
\ MI Ptir.ïiwii'ti :;i.ii'M (jv '(-,-iniri -ijl. A')i\).-i- ^ii'i nr-, iul.
1,1 :.'"'.' 'i i|!&lt;. \r. Tn-.ir; ';0 l i|r«. ii.l in Ui, 'l i|i&gt; vr. G.-r-:.
-•',.- 'l ijr-. \r. II. v. r. ni-iiit .1 ^-'"M j*. ,::i -.'V ,' ' il /L, '. r. Mt-cl.
Lor.den, -l Aji.il. Si;iV.er \:i-t.-r..i.n \'.--,r :.• t u(rn.:i!" d ;t
\ li V,', -t-lü1. f,i |, i.-ni. u.&lt;n.'i'!i.ijr!i vi'i-.l Ijr-t-.r.l i&lt;: :ii'-u i-t«
\':.*' r l'i'./' u 'jl ' ,i. 'i '!. :tv:n.* bi\.'ll il&gt;' imt.'i rn.i' v-'ii il.
\ riB.i:ij. li.kri~;. ,.,;:.•.,- .-.rli-r li.i&lt;&gt;t:'-r- 'irj. (irn'i'.f «yn-f'-n
t' .t ,1 i.,ii..f i'j'..'fiili.' nu', IIH-T nar.i;.. Van \Vr-l-l;i-i. l|.,!,-n
-'il &gt;'l \'-'.: • M Jii'lii.-i l1.''!! i'' al -. -'•:.!•!•!. |l'"ll' l' rv -"i' ''..
l ,1 Ji- .,, ,1 .(., .1 :., ::&gt;.') In 'l l', «:..,- i:i / kkl'll i'i 1.1 -.'ll'lt.i:i
" a. 'm l M::„i..-' a l l '.' . ,7 1 vu. l'-irtnni"! l'.t ^" - u l -.
-D i,n. k. j». . n_/i. IV. ..i.- a l -, l, •' /k. .-r. iu'
M-'iii-lt.ui'. '.'." -. 'i :("" i', 11 I'ICHIM':, .1 u. .T;, t'jt i-.-'. ,11 • ;, if 'i. '"
l':; l, l'.,' '^ /.-r rr'-t .-[t ^i r y ,1. ;:,.;. r. l.»:'.'], li '2-t ne
titl.r1L.-' . :i--.i !.;i'.:c! t-i' '.'- - :. :'.&gt;'•,. \ ~ ,,T .- J V Ur ".i , : \&gt;.-r,l
!...i,ii ;'•.' '.i .'-u '.-.r ir.,.: i'.ii;-.'... *&gt; • ir. ». ii. i,.'i:r.;.i.
Köfiie. K'., ,;j'!_'': l'l..!.1 ; i,'i;--o.,i'i n '..-.&gt;;, il,,'!! _i';t .-.\&gt;- 1:1
oriii:u,r.- .l L&lt;t! :i ,\. ij.'" \ii,. ^, \ i-, i :i ! .'i; i ii, ( \' .u -,'. r[i;s
|i .'.- '•'.:.&gt; n-lk.'-'.l iir.!, m' U.! V.i ..-.! ijii,l.l, iü, •;,:.• !»'.'
t ...,J,, ju kis*,' it S. •&gt; *j. ;, l - - j.' r H', -^ - il ;. i 'i j .:,
:,:.ixk-t. •• ra V i, . :",!. }:, ki-:.".; | ] . .,'i'.; ; ,,,,r
M.,y...(•-..iJ"».l.-r. 'i , .1.' ii l ,:. v;.,'- ii;!.. li.,|..|-i,l. IJ'j'ii l'.-{ ;
v.,:' \ 'i ,li.- 11.-(,[,, i1,- j .v l'":, i., ,1. &gt;,..: H..',:. , -u l'i -tl. :.-.'. .
\'i&lt;- l'-..,."'''}' I. .:•;'.«'lirr. Kr j: IT..'.,!I' i-. .;/- -k ."..v,.-t.
..!
r.-,' : ,. '!. -' -&gt;i'ii « "'i'-:.. Rijst &gt;:.'i , i .iiV i-.= - i. •! • 7'
'.U i&gt; --.- (: ;' l !l •' v.., r. - :.'. e . ., y, \ , i. ::^ N-,-, r:i'i-v i !'J " '. :i.

'i. ,.•".. .,-VA\'Ji-l :.: • /, " .;.--! l .-u l' L l', ''".::. l:..r... '
',r i.:&gt; a'i-'&gt; : virl..- :. ?«?•:•" &lt;-i. i'-:' •• l'.J t.:-,
»:.._•
:-1 -:. Xitrade de Soda x.'-; n.i.'"'•».'.':-1 K ,i':ni.v ;&gt; '•• • 11:1.
&gt;-! ....'l A '..'.:. ,, l', -i M ,. . • l '.., .- \.r '... ' :. '.;
l:i •-&gt;::, u «.r.l vil' ».•:•.. i : \ .... ,.,
:.. ;• i..... ;,' ••;.! -"- : •.-•••. ..• :.•• . .---..- / ,-. • .-.-t .-n.
i..!..- L I-i"-:, 1.' ;: ',. l!.' .i-: r , , r. .). ;..•,;: i,..t

:., ,'&lt; 'i ,1 :, . I. ..,-. L' • *;,,. ,:-, !,.!'. i li.L' '•" n
t 7 1.7 'i. u.,l-.ii..i-- :: -, i-. .'• -. A i :•. M». '-.,'. .: ,-:.t,r
;••.•i. Iï.:iUeu. !'.•' \. "..•. '.; ;, • -.-&gt; ;;;' t ri -• » .: -• •'•.
1:"-•••.-'ui. hi" ".-.• K	•,.-. 'o i. v V..-X. ; • - ii'i.j'.... : ; ,!.

I'.M'.I l'.'l,- .11'..-,- ".V '.. • i' i. 'V, •. :1- ,\:. -l'v:',...;:.-. Jule
i'.i... i '. i i'i. i l :.!i. ',;i ; •., !. i; \,-,!, .• • : ' H ,i :i i't -' j
p r .u. in-; iM-a'. i:. .--•..•.-.• i. Katoen in l".. &gt;-.-t n: •/
•:.'.. '•» '."C. ': .J " r., • ::-'. •-.' 11,,f :i , . .'. l i,:l '., l'k ., ut.
A...-'i.:! i.r.''.!.-. M-1 .i-i.&gt;.'&gt;.&gt;:•..- -S •-•." -i Canibitr
•:.: ..i/'! i •:• l, .:.-!.;-., n l.' • i ,:. ;, - .|'i. n;. .•:•'• i'-&gt;
- ; ::..- ,:•/..- v., t.; i,,-., :.t t: i i-,t. i.. 17 'l -.. ..••-:.. •:- i . i
! i ..i'.-, alk «:!1. .1;-.- K'. ,v, - -. i l	'.&lt;• :,&gt; ". L.;. ...«. :.:' -.
.1 . .: t" -: i.'i l. l i':. -t'j -: t • 'i ..- ,\ i-':' : - :n- -i-'-,:, [i 11 • .';'.! i: ;,
i -. Oiie. ' I.::-:i- ••:••. i-1 -. ';7 ! j •:• ^7 s. .M.-i'A'ii: -7 '.'.
l •.•;- • t ui. :: '-.. ir 11 ;.;..-, ..,-, -j-- 7 :. '1.''.'. Vu-. A'.-.
:: ::. K ••:.- •':: ' •-.". ',.-•.. .; ,- ii.". '-i ::&gt;'•: L, :•'•'.&lt; :'. .M-i A ...
.:'• :'.!- ji-:-. : .'.-,- ! . :.'. -.• K :-•«•;. i-.u, ..•.,-:&gt; .:: ,! .-••
: . i -. -. -.i''II , :'•• : -. t ,i..i«- --..l. K- - :, l v(i .-, :',.' :. :i
... . i:,-.-i i'.'i.i i :? i' :. i- - }'.i::,i- -:.l. :'.- :i« l'. •_- - i - ,.
: '• -. -.:.: .': li'-pcu'-'j-ioiio ^. -:'. A:-. • ;-.l;. ..t, ;.•..:.•,: .-.
i... V -' :'. A,'. .'.-.. ;•• i ^' ; :- Pi-ïroln-.iji : m '. • •&lt;
.,.,'.' ...'•-; L '-..!. - - . J '......'. l.. ;,,&gt;-,. l l:.
i' 'i: llai-ei •'. L':::;Ü.H! -..-:.-.('.•. •-•:, ::: :--..,-:-.•
i •. ' .. -i' .-ii •: i ' i".. AI--. .'.:. .-.'.'.--•••.•.; ..i. :, ".' - i-.;,.

A-' -1.1. .:-'. r-. . i,-. •.':' ,\- K .,;, ;, '.'. - ::.- ';i -i. T!u /• - '•
-.:.. •• '.. &gt; -:: A '.-• -•;,'. •'-•:.-t-..,, l'.,..'.- '. i', r ,. ''...'i-i -.
ó.vikiilvi'i- -;, . '. ',. L-.ioJ - -.u. l'jp.-r :•! in i:: l.u r.
_-'• ,..-'. l 'il.- •:.-. i •_ •:; i" • .1 '.;i . i'. " ; &gt;:. Aln.: s.
1. '.',- -..'. i; L- ," •' ' ,: &gt;..'-.. j'.-,.. .; :• ,i. \ ..,.- IJz?r «.- .

Ll'j'i.-hastf.-. •. A['':i. M i/', in-,-,, ---l.
iJei'liju. .'i '.;.;". -.", • :.::i_-, . •-. i:. _•- |i .- A;,-i;M,-i

».'•.., "i; .p.; .•' &lt;• v .'.v.;- \:,i. 1:1.1 • •.:•' .« iu- ^'i/. n.-t.
Itln. ':;.:&gt;•' f. i'-i*. T.,:-.'1,-;, ,\;.-,l Mi: ilm. i i ;.;n,'u.l . - •.;;
Km. i.'i.':". &gt;"&gt;.',•.-« i" i' A;.,-; M.'i i;ni. 5v.ii'. .i-.i,: .'u.i
Km.- :.:; -•&gt;".-A". -•• ;•-. l!:,', r,:,..iu, ' .. ; .

i;:"l!."r''i i'., .f..',','-''::',-' i: n* i's •:'."" 'iv"^'" '''*:- '-&gt;'• '^ V-1'

:;...,.r. 'l...... i''i-'A;:-.':, V- i Kn:. .',;/-" , •., ;!,,„: .1,. i :;„i. i'l'-. 'i.
Kouleï],. :&lt; A,ii:l." 1. r«c 'i;i:i,i.i- 1.:!). lj:i .'.". ]ir .V;, i
lim, '.'.: l-'l.'.l ,ii |;,„. i1-.',-:,, i: ... "....,-. l!).,. 17..1.1. ji. .\1 i
KI-I. i.'..7u t-ii •Jüh' i.'-;;1', i;..:;":,' .1.. iii:, KM. ••;;.:".
;.i.&gt;!••! Hia. :;• .i.'i ,H (&gt;:t. lii'i. ":.:i". T.,rni; l1.!., r. llü.. 'i'.u
•i! ir..i., ll.i'.u.ii'. ' "
•Pestli." i Ai.-.!. i':-;'i-ii 'k- 'l':i/«.- - &gt;'.. .
Parijs, -'i' Ai, I. .M..!. 7 ,iui Hit T: j' r i. .-i';l'..l" la.l'i.-l
ir. i)- i.l. .\!t; \t. ''.s.7.'i. l i-.l.' v:in ,.Mi i' ir. ?.- 7-'i t"i 'lll- Ai...
f.-. i:v. i. ' ' ' ' . •' .
'l'u-.-.i •].',•!• ii..|i,nli- i,i"'i:i,l Fr. ::.'...':l. Mi:'fr. :iJ..-)ti', liii.

If'wi.' |l'r ,L«'.|i :,!.'...»l:i,::..'l ,V. j'.'-i. Mi-LlV. l'.''.7J, t W. •


; IV. '.'1.7'1.,'i IM'% II Ml l l'l. '.Ij i'i ill'l.uiblr J. lll, l'r. 'lIS.Ii'1!.
'
x.i.i '&gt;|. l l'.-. ; (.7"i tn l.i u:,- l in. l'-.
71.75.S .irifi- |i..-i-. lu ip • luï-ii.l .(t. i'ni.JM, M, i fr. (',1X75, l in.
v.i.n'Mi'1 ir. i'.r "i'i fi l ai-'.'- l ui. l'r., c.'i^u.
', Sn:\ir. s- p. !.: ,l.,,l.l, N,i. lll iltll-, 7."i.-.'."i, Nxl. 7 11 l'r.. f.S.i',",';
i tüif Xn.'S ii. r lu.-.|.i'i.,l.' 1111:'ml :&gt;. li-.i,;i. .Mt-i l'r. rl!.!iil. 4 ut.'
1 i;.'i M.i'iV. c--&gt;i.. ir-.'-i.V. IV. 117.1 ' ' •-" '' ' '
.
Aulif&amp;'piin, •' A|n-il. l' irn'-i-nm k .ju ; ,.':i-])i(ii!i, l i'r.,'7:i
n -... |. p k iiit-t .vu-i I^Milcl i !i»t&lt; |,ji.,.K..« fr. '71 a ". a. -ïi'ji'i'
u.i i a'. 7' :'. 1'- K' L" 1: \\ ill'"V /,*!'! il ^'1 -. &lt;ir:llliil l'i
l'Ill: Ilavrc, t A;'ri,l. Katoen k:'.ln..: iitk'it'Sit l')(&gt; bu.''/itT i,i-il.
. '1. i:ii*i 1:1 ' in . l.jr ' li*. 71 :&gt; 7a. ii,r\-\j"'i (e. (i7i^. p* i' .luli
IV. ti'.l. Eo.fIIe k's.'lil; yi-:k"i-l.'' "&gt;i.&gt;-i' n. ''Ji.iii'iw'a IV. 77:T..:H
.ti.l. itii-&gt; ii i'r. 7-&gt; en I' i' Iju. Ilaiti l'oit.ail-.l'l'iüi e, vii'i' i'1-i'p.'i-,
j (ai fr. 7'* :V 71 in i'nl"cp''t. • , '
' • Fcstli. v Ai-i-ii. Granen. T.ir»v jicr' K'uti-iiiS.iului il. 1.1. l j
l 'kiMjiiiS. II: ll.-.'O 'n-ik'i'jj'ors. ll;ivi' \&lt; i" Mi-i Jiaii il,, n. 71
. k"-;l'v:S, IU l.'.^H V', rk.i '['.T!,. 'Milis v:ill 1'n.l: iit prl' Uiij.l V (l 7- 1'&gt;
j k i-p..r.. il. 7.Ï-1 viTk.».|ii'W. ' '. "• ' • •
• Antvfcr&gt;!&lt;-x. "i '.\nrif. Kofüe i»)ui '-n »&lt;a.]re' lü.i.-Jvl i"
i ilr ,1'ivii- li.ni'l -B'.likoiv ll.ii«iirit-l- -s jit't. i. i Li '« Ir. .14 ''i
• in rn:r. .Huiden. \'frk 'c';.t li" dr lïu in.'--A\ie. ;'i Ir. U'-^'j
l."ii uï/. (ilii.'i ul.iA \ai! l'r. li'.) :'. ,"-&gt; rh -'''IH L'i-/. l IIUli.1} V.ttl
1 l'r. 7a a »a !|i- f l U k':l'i. Wol. Vi-rkucut U l lul. \,tlc
i -|ji' l'l.ilu Vu -in b», hi.iji sii" u» «1:1". Sfllpctcr. C.i:it i.:cl
v.rk.i'iji v:m l.'.OMl kii« .i Ir. K&gt;: i,|,rr t;.O kil'!. Talk.
V.,ii'. l.-i l'iit.i SkijUi- ni'i.l'ii irj'S'i.iil &gt;a l ui .in a iii.tcii'lur,)
i' ii / a. , jvr .in liiln. Petroleum kiilm: uriM.!1. Am. r.:
l.."-.l. . . : . . l'r. a7'.&gt; l' »;J-i tel.' l'r. i'7' ' :i \iTko:. ;icr3.
'
ln.l. i,i' Lvriu^. '-u uicti iu l'»-o. Allivutf 20UO bwt. Irk»
(l.!, i.s,i lll') U'i l'r. 7 '.[i Ifït-r. l"&gt; April; Irkn-Nikulujcir
IM l l'.l u1 IV. M..',u p-r &lt;l Ajiril ti- l.-nr.'U.
Bordeaux, -1 April. Torpeutijaolie vwtir. Jltn oottert
ir. i'.':'^ }i,-r 11)1) kiii&gt; xrij :i:iii b,/';ril.
UcaLH, :i'i M,:„i. Koffie u., t g&lt;jcl&lt;-u bauJtl. icrkwht
iliü- w.i'k H'i') bu. l'o.".u* ii-'j, vi'riu^ilflijk a l*. 1-iO mttceuijje
. k..rt ie.'; InOo lm. li.liin :i h. s.', CDO bn. Siililui M U. 25 «
l'lj :i.,.r kr.ui. ui IVin bn. Kiu prij»g' btriui. Suiker, lubnil«-h
^tri!!'. uiu et-ii oio/"l vrtii lO'iO n. op levtriiiis tot U. 132 B 133.
li'.'il.ii ii ilt- inaikt vu-t'-r tlo^r tlvit h'ju^t-reu wiüselkuen en
i-..i-'il in. u Is. l:i'i. Huiden «til ct&gt; blijvm «l«.-hu vuur
il ui hjk'.- b.' »lle b f-- i-r J. I).- prij* u zijn ttamv. Omï.t &lt;le«e
«r.k il!:i).»t.ik-, »«anan *il) M.-A. ««u- »»n 13 a U kil»
u U. l l'l uu-t Uit.,,.', (-nu ,lri,ge ll,!i:«, 10 kilo, a l». 100 met

la. &gt;",. VuuiruiiJ ui, hdl^u ijü.iioi stuk». Axnfuidelon tu^t
vtiitii^ vi'^ui;, u^k in ilu di^jfJiiiblt.- vuuri-uutl kltiii, t^uijtekltiiio
, j ;irtijtjfs Z'H-t.' S;r,!tiii«; vuutU-u kuo|n-rs tut U. 3:25 a ^30.
Olijfolie ftil. M-.-.i boisaM.i v^ur Gatlijiuli la. 12? i liï, «t- '
ifii-.; s.'i'.i.i,:v &gt;.i|,tii;iK K. K,') n ie*. Petroleum kulm.
Ger.:1. iii ki-i&gt;'ii in iliih-ittli- KUiatiiin!^, tvnviji g'nttl'. iu vaafjts
jirij-li'n.'il' uil blti-f. VtTknchl + a r.liui) kn. B l». Si '• 4.
Koningsbergen, 'i April, Granen Tarwe Injfi.r; KOKII»
' ilnintv-r, Iwu UI ai! U' Hui. 133. voorjaar ea Mei Juni 136's.
Girst uil. ll.iv.r !l.,uw. Iw) Km. lïl. i.wrjair UO. Gele
Kr.Urn Uui. lit''i-&gt;. iill'-i JUT 1UOD kilo lullguwit-ht.
Dantzig. -' April. Granen, urnr llunnr, on,zit 150 Ion,
1,'lllt': Itiil. ,'U' ,i l'-1'.., Iichlb-Jllte il lli. iM -'i'S. HlHsiïl'hl'
Hm. Isi it il.), April'Mii '12i. Kuiltje uuverauilerd, lafl) tt'
lu,.,. iiilaii'1-i'bi Km. 1Ü3 l.'i'J. lut-u Kut.iwlie 13i), April/Mei
i-ii Mei Juni l:ij. lijne (,'-,,t Km. 13ii, grovt 16U. Gelj
Kuok&gt;rn-.ea jtm. \'M ii H'). lUvcr in loco Kin. 13'J, all»
l&gt; r lOi/'i kiiu «,i!lxf»ii-lit.
Stettin. 3 A|.rii. Granen, Tnrm.- itijaeu.l, ]«r voorjair
't'.iu. ^M: M''i Juni 2l'.i. Ko^p^vuai; per vuurjnar 140.
M&lt;-i Juni Ui',..",'). R.&amp;polie stij.'tfi'il. April Mt-i U'J.!!0; tu
&gt;,'iiO.i. i;T. Spiritu1) iu luro SÏ: vuurjaur jl, en Juni Juli
;2. l'l. Petroleum prr mj'ar 11.90.
Stettin, 4 April. Granen. Tarwe !lauw&gt; per voorjaar
K u,. 217. Mt-i J-mi i!7; K«jiit \-,-t. per vuuijmr Hm. 148;
M.V Juni 117. Eaapolie'»'.:i;"April Mei C'J.50; S. pt Oct. b7.
fipïritii.i iüIJ.Q jU.-O; voor;:iar U.ï'J; Juni Juli 5^.3Cl.
Pttroleum |J,T u.ij'nr ll.vi.
San Francisco, l Ajiril. Granen. Tarm zeer \ut; imu
li-r. irt 7 - |"'0 ij'nr'. r \nu 5'iO U' uvt vraih^ najir l.iverjwol
ol l'r. :il Jïper l uu kil.).
, KeT-Tprk, l April Kito;-n: miJ.Ü. ailiii-r 10",, te Xew-.
(lm ui., iu'. -. Vrtru-Fbin: n;«e 1.4», pi-rai. 11 ; &gt;. t-.-
l'bilai'-ijilii.-i 11 j c. M.-rl $ j.i'i. Mui* fi'l en ru.jJc WiiitiTtarwe
.-: l.:ii;, l!i.. kufii- l", i. TU Muu'i.Tiitli.i Miiki-r 7'ji'. Vracht
\.j-jr (iram:i '", tl. Hc-t/ïl 7'. t-ii ."pei ."..j c. Keuifl: Wilt-oi
p r Mi'! 7'. r. K'iiO''u. l.« uiMill. Juui-ïn-i hupiu;! 10.SI i-.
A l,\-trr vin kut'.'. :i o[i bul u 5."O" bu. Titvotr
baar*Eugel:i!.l 7.ii:'l.
Kew-York, -1 Mairi. Huiden g.ivtl t!i'vra:ig.l en vmt ia
|ir;&gt;. is.ji-.i; ,lr. M. V. in l tf lot il a l ( c. rerkoebt.
Terpentijnolie iiit-i Wpi-rkie vruaii. inrar Tast lut 8iji i a 31 c.
ut i";' v-. \ rk. Harst vu?t. tu ^ui-il ypvrmi^il, 3UOW vjs.
^-"-l .&gt;:r:ui. J in l-.iio tu up li.-u-ri:it: t.ii .s 1.11:2'2 a l.'jj rerk.;
:;-."'i i.-.1 .",1 t .1 s l.'Ji :t l,7'i. Hooig j."H-'l jt-ïriia^J en.

i:i e: T. v: u.' dtx'iLf. Petroleum. l!u«r 111'l z«ur »eiuis ,
vr ^ :':"i i:;, v. rk. tot '! . a '•',. r. (-era:!, tïinw cu lager;
•Jïi..n t-.-* \f',-k. t'.t 11 'i a 7. r., liïl t* altiuiurt'tut ll&gt;2
n - r . * n f! ,tt'- 11' i i-., iu ki-tfit a l't'- 4 c. i,:ii_clnideü:
•,.;t,. i'..;-'.'.i !,:.«•.-.•.:••« l Juli :v'.,'.n-j i irn!. tog.-n t:i/iJl.Q54
i-i i-77. Spek. i r ."*-: -'•/. i;."'il .'-^vratj.l. lua-ir ifu-t-r, IjO') kta.
\--'&lt;. l'i: •"• - n . -. \',.n' i.'.'.-- ( .i'ür, O', a 13 c. voor
- _- 1. .ii.: iii '-2 S::.jri, Keuzel ;;-t-J U'?vr:ia:iil in lot-o, en op
' l-\ f-.r. i .-.-il' i,-_. r. 'jn'i'i t?, t'.t :&lt; 7.:&gt;-&gt; a 7.i1' xirAOi-iit u:i
;-.-". -.' t-. ".• . -.eri.i.' t&lt;t s .M 2 a T. T' p-r April, s 7. IU a
7".' i" ' A-- •• Klaverzaad lütt «lii.i.; vr:i:-*r vuur uitvoer;
i1,- i. ',:.vii'.'l" ;? ^r.'-vt en il-j Llurkt li.iuw op 7'» u '•-. r. voor
l'.i'-- v:.--,.,-u. Spe.cerijC-n \..ur.ili.:-iuj' stil, miiar va«t;
l'si,-.:&gt;: -", :. ',"• i-,. .\j/.::ij- . "*" i. S'J c.; pruilt l!:ua\ i:i C^ïSia
j- - :, i1-1 ^ i1.; ^i.Ul ti'j l', p i' l*t* :i •; v., prima
Kruull:.i.-'i:i ::&gt;'. :: .'i s i-. Suiker m. i-r '-T a-'-i. Ju atlevcriuit
-- -r. l J .:i i- i:r ,.,1 r- il.-u ia 1X77. vn 'lc v.&gt;on-:t:.il alhier
•..-i.' i i.,;„..f :'.-', i',,-:. M.ir.-r iluii ia A' l'-'. !&gt;• ,,aiu.)cr iu tl«
4 fi . t,:: ]:LI-II' :.;,selli ? ,1,-1't J Jrtll. is' ^i'i''" t'Mli tik'.tier tl;tll
i:. 1-77. n i. iil ';r tie ii.,i''%i v.5t r i? ..j» 7 - a ' - t-, vuur fuir
fi ^ ,-!• r ,^ Ttilk -"il x^,,r i:::\&lt;»r eu loi.riiiiitii. jft-vraagd;
;- ','j -i sj' :'. 7 .'. \tik".-,.t. Tin v:i&gt;t. iu t ^«'iurrkli- vriiw.
l!ii..-'i 17 ; '• ".-.r,i:?.-: iliilai-.'.i 11 , a :', f. Tabak.
K' ..'.r.:''iy r. UlIJk u-, vra-.il. :U7 va. vrrk. tut 3! 3 a 111; c.
Vr ij'.i::. KI' «u- i;".'.l-.- vi-:;,.; rn'iir ? lid(a:''i:iute vi&gt;or 'Gruu--n
l ; O ; ^ ! j il. |'ii- O1' ii' ii',.ir l.itti'j'"'&gt;l p. r ^eil-ehiji: per
-' .-'li' • •! 7' ; tl. kaïr», "p I. ni.lt-u i-p 'l J. t.l nt Uw r
b,iuk^•.:--.!- .&lt; v.-.;'- rt i.-7:; o. up AI.:-UT-'.IÏ41' s a '•-j t-.
St. Thomas, 17 M .;;i-.'. Ciiapichehout va-t iu prijs j
S.-" ; p r l'"l «-.-„"j t'' K-V' ll.i.tl. K'i't Libcrti-, aU Ai|uiln.
Louisvill?; &gt;- v. .:•:&gt;,. Tabak, l ie in-i-ki is ge„uiuit-i:r,l,

\ •;'•:, i!.'- M".'; 1;7'-' iii.'.'i..-.,irviiu |:j-i' v.-.i'i In-t ,riit-u«ii
.«:i-. t'i '.'~ \.i !,ot 'i.:,!. . ;.i:,V''ii- 1^--. fu \:tll 11 :t _'ewasv.iH
&gt;:7 n.r.' M i.rk'-f!,t Il7".7.'vii. Mt-u ii.'turt urJ. Liys
.' r : • S •; a '.'.,',". w.,1-!- S-;'..-&gt;'.' a. S: i;i:ilil-l a, icn-Jt- ii« k:e
s' i1.'" a -".;", ti: /'t:.l-i' S S..".'l :i 1.. i&gt; J. lii-iil bl:i.l !i t a J ;
.-»;•.. S i a i1.. n::.;.;il .;,.,!. '.'.-iit « ."&gt; a B.'ö'i; ziv„ar S fl.SO
.: 7 ' '. -:" .r 3 _•- .! 1: :.!-•.&lt; 7 'J O -'"'. t-ll 2-.v''lv O a UV5'J .'.
B iu'::r-". 4- AI-I'Ü. vatac-il k li-i.. nifii i:ot.fn g.)i,J fair
l' ':;.'::i.' " ". :ll l i ' li' ;,; ii f 1!\ 'L'üOl1. l'iil1 Hr'.'a'. b. iilelll,
•' '• v l. &gt; i1.: ''U'1-* 1:1 'v ^'-.:''.it l :a t.'1 K.'-'|&gt;'Ot' hit knliaal.

i,',-,:i ;il--i"'..i iii' ]s77, / • --r,/. '.-:.•'n-1:.lm, t r.t.-/,ttn vuur
K:t;,ll I; ::!• l.iti![''''. 'l.'''f hel KüMiIil '~~&gt; • fll via ilu K.lüp .


• IVilmin^ton, -Ji &gt;l...:.vi'. Harat \ "t: Ptr:i:ui\l i? l.Siij,
iM v.. '- &gt;: 1.'..'» ^vliK'ii, T^rpcntijnolis v:i-t a M^ c.
B^ltimoro. -:&gt; M..arts 'Tabak, Ur imuvoer van MarylauJ
ui lli,'. !.••::,l &gt;•&gt;"... l'i...ü- 'di' in.U'kt b.ij.'l tll. \"an Mnrtlautl .
'-./.l u , IL.-, k:,.i::t' ['.rii.;;*? vour UIIVÖLT 1:1 ii'.men, iltitb tle
ir. ',' 'i' :i:-t itvej I:L': prij/ n uiivcrainliT.). lic ijilal. vju den;,
i--'.-!.' «::'* !:'. :i. vu-1 ir;..'i' ,1, a lift tori:: jiar. .U uii-t EUO güetl.
:ii- ,li \L-n-,,re iin'V.i. i-t u ,1 tl u v,'l'\\;i.'htvll. Vuoi' Ouio brtt;iau
L', i n k-i.);.'.!!-;, t-ii i&lt; iU- markt vu&lt;&gt;r il:o si&gt;-)rt' zeer ilmu.
luspecliy ''It'.'i' «n'^ Iü77 Vil M;:r\ !:illll. Jllj OllilïtD 15 Vil, Vir^
nt -v.'i'l.in. -ti. /iiuii l-i'ö-\'i. ritujiT ii:tar HreuivU per st.
t'iit-i li'j vu, kintirky, J" Virfiuif. ,3üMirilaiul ea 33
Keu

slurllJi' tfli [i'ii L'o.S'1."! vu.: iu.«pei-lie tlt'ZC wet-k
:il- ;iit',7 Ml., to ialiell ;7,7o'D vatfll Uitvoer
v. u M u-vla: J .ui Oliiu retli-rt l .lai.iuiri 1»7&gt; il'.ni-1' vu., uaiir
ili'. kii.-t /"MM), vu., te /.:uuii -71'1-, bl-jl't \ourr:ia.l alf bu.vcu,
. ;.".:io7 vu,.t'-tt"i i'-Vll vii. iirl»77 : uitvuet vau Marylaud cu
Oliij 'l';,luk &gt;,il rt l .l.iunari IJ'.MHI vu., waarvan naar Itremen

tu 11:1 ir Ku^eliiii.l '21 \u., t'ii'iii 1&gt;77 nnür Dreinen 1590 Talen
iiua.1 KiittiTilJiu ^t'i.'ii vLitiii, MI uaiir KiiiTilaft'! 10? vateu. ,l&gt;o
u'-tt'.rin* i-i aU v'1^:1 : Mtirjlaiul brviort-n ^ '2. gezu.ud oitl.
S --"i" u :l: ;mJ .Iiiö-:s :!.."id'i .j.on. iniildfl -i O Wi 7.0H ; gued
:'t nlai .'-Jtl S » l", l'u'"•)' S 10' u 15, l'[i|*r Cutuitrv $ 4 a j(l •
iii.-iiur. .cr;i:u.il'!r:nfs ^ ^ &gt;. Ouiii itii'. ii jruotl ordinair $ 3
:'i 'l.'i'i. ^ri\i na.'UliL' Vu bruin i» k-"»" u ti. miduYl l'rïiai róód
l* •'ï' ('-*&gt;u II *&gt;; 'kT'^' " ml'fl-1 ^t-spikkflt] S ti a S. fraai geipikkfld
i ii -'''tl iv 10 ;', lr&gt;: Hiiulutki onllnair :'i poeilc. Ltii» $ 3 n 0.60
; (.'liirksville tlito ft.'M u 0. ord. bind -3.3(1 a U.50, li«r 4.goed
s '.l. a l-', fra.:i t n g;li-i-tioiis ^t \- a lü,- Yir.iitiie ord. t-u
jrocj dj l.iii.'* i&lt; 3.00 u 3.50. ortl. a middel blad S (1.00 i S.UO,
! l'r.ai :i j;.ii-.l dit,i .* S :i lu. si-kvlious -vour uitvoer ^ 12 a 10,
[ iroiil- a l'ra;iit' Sti-fli-n .&lt; 1.30 3. Vrachten ónvcrauderdt naar
i livfiitu vmir )(iir\lund-'l'nbak 3". Virjrinii.--.37l3 ii 40, «n Ken«
tntky li'l\, .m.ii'ic. kut-'ii l', rui: op Luudkli vour Bankw. 6U d.
, /ifit ^1 l &gt;3 a S3Ï... cu i p Aius t-rtlaiu 3'J:&gt;.s u 39^.4 c. ' '. '
: Havana, 15 Maart. Suiker met cukele verkoopon deze
i \vi-ti, t'ii voor. got-ili: C uirilugaal m-rd, rl. 9 liciaajd, maar
»v, r:.it.|i.«' wai-fii Je piij/in laiitT. De' ui.,rkt was Bok stiller
ilan LEt'VtO'iiiltjk 0111 ilt'Zt'U lijtl van • het jair, en de kaopera
\t'. i-iiiiii o]i gróotfre' aiiiivovreii, daar tle markt dan meer kens
i.jilfvrrl. Aauioir seilt-rt l Jan. 42.Ü3S k u., If2+? jk., ea
rn :!5ul'J vn, tigt-u'-100.Tl7 kn., ,110.737 ik., en 4S.92S vn.
iu A... IV-: a!-f li-vt-r.l 4'.).332 kn.. til.T'Ji k., in dO.fiUO vn.
ti-si-ii l.sirkn.. asilO &amp;.: t-ii i,lOS3 vu. iu l-iJT-, voorraad
,:."J7lli'kn.. -li.Sïjök. en 10.073.vn., tegt-u 7i.39l kn.. 57,ï*3
/k . tn £l,-llii. vu. iw 1177; uitvoer van hier tn
; visL'rt l Jatutiirt: • • • . '
. .
.s,.jii(-ml)i:r.. -• - . ... ..al) •• - . • . •, '
i:,:it«-.i- 'i NI. .. '„• - .. _.. :m -f- .• i ,, ,
Bonze! IrH knl-urr \I«IP Wili-nx W" • ""'" '"'' ia''''' / l!"'"' l
en i!i/..":jirij&lt; lilijf' -i.'i'U iri-vr.!.'^'! ''l' U-ivj-inj; .11' i
«-'.-rili'iK. iclfili- pr.js )&gt;Fviirili-ril. Spek. lii'-t pji'ilc.vrnllj»; rrkm-lit &gt;i-f.
S iii'riidc iïi''"i&gt;t'.' Jiiiilijt-n l'ico. viiir IV. 70 ii.71 v-ur Jikkc l'il.y
mini, il. * i'h v n n Ir. 7*'l i'i ?o:2 vi^ir &gt;ln»rt luiiKllrs. Hij L'CI'^I'
nit;irt lm n IV, 7a'a 71! v,.nr dikk" lii''&gt;.' la'illlrs. IV. 7i
vu.ililiiiu... .ioug niiddli!* i'.i fr. 7"':ii.7ii \'i'ir slmit nmU]i:-i. (ii/..
-.-!i.|i d n ,|.i''^''i' ill v:-n Ir. .M' :i l', l vuur l u-u liet uild. op
II-VL"r, n.- Mi i' a. i d in.ii (i-kMi-ii « i'r. 0!*. (ïranen v -t. d.).-;.
/ milcr L'i'inti'il Iniidi I. '
MarMclllo, S April. Tarivo. Kuluu: inni-kl: vnkuclii lf"j
Niturdi'H vun Ku
Kriin!&lt;njJt i'. ,
' ku. zk.. vn, ' kn. TD.
l'1.301 CT.L'lö51,327 41,799 50035
7.-VJ2 1,407 33S 14,1)2.0 3,842

--- 300 150 : 125
4.7SS ' li;i(J9
Xiil'lt'ii van Kiiro'm, ' , . : -, v—-.
A.i'U'H l:iiul..-ii,. . . 3.UM '—•. 1.301 .—'
Tutaal	lT.iiilj (iS.lIj* iu'.nï"(i.lUj 60^052
De uittu: r van de beide h.iivm touiit tx-n vermindering v»n
1711 ku. ui tiO:!7 TU.'tn /k. vurgelfktn b(j 1S77.
Gnajaquil, 3 .Maart Cacao viioriiluieud-jirvraajid, en de
uo^stb rivlitiii 7ljii nrtlrr Bh-t-ht'-r; di- Aanvucr 'in Jau. eu !'ebr.
w:,B .*,in i|i. kli-iinr ilau'in 1*77. eii iu de Jdn hrlft viiu Kebr.
bviliui-L' tlie 3-iH .in. Arrib.i 7.."&gt; Malau; en 7M Mailialn.' die
iu&gt;|h(-iit-vi-lijk S I7'.i. lli'/i. n" i"J' « opl&gt;raelitcni Teru)oe,lelijk
• /al J,' pnjt M.I.; v, r.ler -lij^i u, vo'.ral tluiir er nog «rlirptu
oubcvrxcbt zijn, Xuen up Lju'lcu 90 dagrn £icbt 3'J1/!!
-.U.,?
'•1" i

</text>
<image timestamp="2002:10:26:12:55:34.00" size="911961">D1000JZJ.TIF</image>
</page>
</document>
