<?xml version="1.0" encoding="windows-1252" standalone="yes"?>
<!DOCTYPE document [
  <!ELEMENT document   (languageid,fields,page*)>
  <!ELEMENT languageid (#PCDATA)>
  <!ELEMENT fields     (Bron,Datum,Pagina)>
  <!ELEMENT Bron (#PCDATA)>
  <!ELEMENT Datum (#PCDATA)>
  <!ELEMENT Pagina (#PCDATA)>
  <!ELEMENT page       (pagenumber,text?,image?)>
  <!ELEMENT pagenumber (#PCDATA)>
  <!ELEMENT text       (#PCDATA)>
  <!ELEMENT image      (#PCDATA)>
  <!ATTLIST image      timestamp CDATA #REQUIRED
                       size      CDATA #REQUIRED>
]>
<document>
<languageid>21</languageid>
<fields>
<Bron>De Groene Amsterdammer</Bron>
<Datum>19320625</Datum>
<Pagina>22</Pagina>
</fields>
<page>
<pagenumber>1</pagenumber>
<text>
NAAR DUITSCHLAND
Prosp. en inlichtingen over onderstaande plaatsen en hotels zijn gratis verkrijgbaar bij de voornaamste Reisbureaux.
Petersbera
Kurhotel Petersberg
Königswinter a.d. Rijn
10 M breede autoweg • Tandradbaan • Economische prijzen • Gezicht op den Rijn en het Zevengebergte
R AD-RENT H F, IM HOTEL KAISERHOF (bij het
U*V.Lf-.L».tJll A IIAJUTA aan den nieuwen autostraatweg A'dam
Oldenz.—Berlijn. Pensionpr. van f 3.50—f 4.—. Vraagt prosp.
route Keulen—Trier. HOTEL HECK, pr. bergr.,
omg. 28 bedd. Pens. pr. Mk. 5.—. Uitst. logies,
prima ref. Geognostisch Eifel Museum.
(Eifel)
o rl ~Pïi» Meest aanbevolen zijn: Hotels: ZUR
d.tt. lUJIl VILLA FRIEDE, DRACHENFELS,
t.o. Zevengebergte
(Drachenfels)
RHEINTERRASSEN, KURHAUS en
PARKHOTEL, Pensions: VILLA ELISE,
OTT, HAMMES. Pensionprijs in hotels
Mk. 5.75 9. . Pensionpr. in pensions Mk. 4.50 9. .

HERZOGL. SCHLOSS HOTEL, grootste Ie kl. hotel
ter piaatse, 150 bedd., 30 baden, pracht, ligg. a. h.
bosch. Kam. m. pension v. a. Mk. 9.—. Tel. 247.
(Thür. 850 M.)
(Thür)
HOTEL WUNSCHER, het zonnige en stofvrij gel.
hotel a. h. bosch. van ouds bekend. Pens. v. Mk. 8.
tot 12.—. Vraagt prospectus.
T A IMTVÜTTT1 K" T?iin (en Zevengeb.) Hotel Decker, 50 b.
IjAIM Uöi^lY, ±iljn Volg. J. P. Spr.v. Eyk Een liefelijke
ijfpl. in 'n heerlijk oord". Kam. v.a. Mk. 2.—. Pens. Mk. 5.—6.50.
verblijf pi.
rp 4 TJ AT?'/ Kurhotel Schiesshaus m. Dep. Zonnig en stofvrij gel.
± ./YOA-EWJ pam hot. a. h. bosch. 100 k. alle comf. Zwemb.,
Ten(Thür) nisb. 10 Autob. Pens. f 5.—7.—Vr. prosp. Holl. refer.
Hotel Schwarzer Bock, eigen badh. in verb. met
de warme bronnen. 280 Bedd. Alle comf. Log.
met ontb. v. a. Mk. 5. . Pens. incl. Thermalb. v. a. Mk. 9. .
NAAR ZWITSERLAND
BERNER
OBERLAND
(ZWITSERLAND)
1356 M. BOVEN ZEE
Ideale, hoog in de Alpen gelegen badplaats en sportterrein.
NIEUW ZWEM- EN ZONNEBAD, RUST GENE

ZING TALRIJKE WANDELWEGEN.
Prospectussen en Jiotellijst bij alle Verkeersbureaux.
ARO8A. SPORT-HOTEL V ALS A N A"
Het beste Hotel voor U. Modern comf., Ie kl. leiding.
Matige prijzen. H. C. ARNI, Dir.

BAZEL. HOTEL CONTINENTAL.
Tegenover Centraal Station. Modern comf. Matige prijzen.


BEATENBERG.

HETDITZICIITSTERIIASiANHEIBEiNEIIOBEILAIID
1200 M. b. Zee
GellL prosp. bij de Reisbureaux gratis verkrijgbaar.
BEZOEKT HET
MET ZIJNE
ROTSEN, GLETSCHERS,
RAVIJNEN EN WATERVALLEN.
ALOM BEKENDE ZOMERVERBLIJFPLAATSEN
IN HET GEBERGTE, ALSMEDE AAN HET

THUNER- EN BRIENZERMEER
BERGSPORT - TENNIS - GOLF - WATERSPORT
HOTELGIDSEN, PROSPECTUS ALSMEDE ALLE
INLICHTINGEN WORDEN VERSTREKT DOOR
DEN VERKEHRSVEREIN DES BERNER
OBERLANDS". INTERLAKEN. ALSMEDE DOOR DE
PLAATSELIJKE VERKEERSBUREAUX.
BRUNNEN
HOTEL WALDSTATTERHOF
220 bedden. Pension vanaf frs. 13.50.
CELERINA bij ST. MOR1TZ, 1750 Meter.
HOTEL CRESTA PA L ACE
Engadin.
Pension vanaf Zw. Frs. 18.—.


ENGELBERG, Hotel Bellevue - Terminus.
Boven Luzern. 1050 tot 1800 Meter.
Ie rang. 150 bedden. Str. water, orkest en balzaal.
Matige prijzen. Pension van 13—16 Zw. Frs.
ENGELBERG.
en centr. verw.
VILLA FORTUNA. Mooie
appartementen met bad. Keuken
Aanbev. AMSTUTZ—MULLER.
M ONT AN A-VER M AL A

Parkhotel
Rustig familiehotcl met groot eigen bosch.
Ieder comfort.
PROBLEMEN

SCHAAKPBOBLEEM No. 323
van P. F. BLAKE.
Oplossing probleem No. 322 van
Dr. H. v. Gottschall.

1. Ld5—hl, LcGxhl, 2. d4—d5,
LhlxdS. 3. c4—c5f (2.. anders, 3.
Pd8—b7ï).
l	, Tblxhl, 2. Dc3xb3, Thl
al, 3. c4—c5f. (2.. anders, 3. Db3
a3=F).
l	, Dg8—g2, 2. Dc3—gSffó—f4,
3. Dg3xf4f. (2.. Dg2xg3,3.c4—c5f)
l	Ph2—f 3, 2. c4—c5 judo—du,
3. LhlxfSf.


Correspondentie-adres: Dr. A. G.

Olland, Burgemeesterpark 3, Drie


bergen.
T Wit: Kh7, Da8, Tb3, l.gO en g7,
Pa3 en g3, pionnen: b4 en f4.
|f Zwart: Kd4, Tel en dti. I,d7, Pf2
en gl, pionnen: b5, c2 en f6.
Wit geeft mat in twee zetten.
Oplossing in hefc eerstvolgende
nummer.
BRIDGKPKOBI.KKM 28.
Z heeft gegeven en biedt: 2 in H.;
W past; N 2 in S. A.; O past; Z 3 in
S. A; allen passen.
W (!) komt uit met Kl. 10; N legt
zijn kaarten open; hij heeft Kl. 2 sec.
O legt Kl. a. Daarna merkt 'i. op, dat
N de Leider is, dat O dus had moeten
uitkomen.
Wat moet geschieden?
OPLOSSING BRIDGEPROBLEEM 284.
I: Z: Kl. 7;W:K1. 8;N:R. 2;O:K1. 5
II: N :Sch.a. ;O :Sch.4 ;Z :Sch.s;W.Sch.a
III: K:R.3;O:R.7;Z;R.io;W:R.4
IV: Z:Sch.s; W:Sch.6;N:R.s;O:Sch.h.
V: X:R.6;O:R.&lt;);ZH.g (!);W:R.8
VI: O:H.4;Z:H.b.;W:Ii.v.;N:H.a.
VII: X:H.2;0:H.5;Z:Sch.7;W:H.io
VIII:]
IX:[ Z maakt altijd nog Sch. b. en Kl. 10
X:)
Geeft het O iets, indien hij in VII H.h.
neemt ?
VII: X:H.2;O:H.h.;Z:Kl.io( !);\V:H.io
VIII:»
IX:i X maakt thans H.S, 6, als negende
X:' en tiende trek.
B. M.

Correspondentie-adres: Secretariaat
v'd Amsterdammer, motto Bridge",
Keizersgracht 355. Amsterdam.
DAMPROBLEEM 326
van A. FISCHEK te Amsterdar
Zwart 11 schijven.
l
6
11
16
21
26
31
36
41
46
Wit 1Üschijven.
Stand Zwart: O, 9. 11, 12. 14, 10,2'
28, 2!», 33, 36.
Wit: 21, 25, 27, 31, 34, 37
42, 44, 47, 50.

Wit speelt en wint.
Oplossing probleem No. 325.
AVit: 34-29. 32-28. 42-38, 36:20,23:5.
Zwart: 24:22, 22:33. 33:31,15:35.

Correspondentie-adres: K. C. Keiler,
Valeriusst/aat 40 boven, A'dam (Z.)

</text>
<image timestamp="2002:09:27:02:26:55.00" size="170886">00000ACW.TIF</image>
</page>
</document>
